{
  "id": "DID_DefenderPistol_Basic_C",
  "name": "DID_DefenderPistol_Basic_C_T01",
  "description": "A defender trained to fight with pistols. Defender Training: Consumes 33% less ammunition and weapon durability.",
  "rarity": "Common",
  "weaponType": "Pistol",
  "attributeCategory": "Defender_Pistol",
  "attributeSubCategory": "Defender_Pistol_C_T1",
  "icon": "/SaveTheWorld/UI/Icons/Defenders/T-Defenders-Defender-Pistol.png",
  "largeIcon": "/SaveTheWorld/UI/Icons/Defenders/T-Defenders-Defender-Pistol-L.png",
  "tags": [
    "NPC.CharacterType.Survivor.Defender.Pistol"
  ],
  "traits": [
    "Item.Trait.InventorySizeLimited"
  ],
  "tiers": [
    {
      "tier": "I",
      "minLevel": 1,
      "maxLevel": 10,
      "rating": "Default_C_T01",
      "xpRow": "Defender_Common",
      "evolveCost": [
        {
          "item": "peoplexp",
          "quantity": 500,
          "name": "People XP",
          "icon": "/Game/UI/Foundation/Textures/Icons/Items/T-CrewXP.png",
          "rarity": "Common"
        },
        {
          "item": "reagent_c_t01",
          "quantity": 5,
          "name": "Pure Drop of Rain",
          "icon": "/SaveTheWorld/UI/Foundation/Textures/Icons/Items/T-Items-Reagent-C-T01.png",
          "rarity": "Epic"
        }
      ]
    },
    {
      "tier": "II",
      "minLevel": 10,
      "maxLevel": 20,
      "rating": "Default_C_T02",
      "xpRow": "Defender_Common",
      "evolveCost": []
    }
  ]
}