[
  {
    "Type": "BlueprintGeneratedClass",
    "Name": "GE_HuskPitcherRangedCooldown_C",
    "Flags": "RF_Public | RF_Transactional | RF_WasLoaded | RF_LoadCompleted",
    "Class": "UScriptClass'BlueprintGeneratedClass'",
    "SuperStruct": {
      "ObjectName": "Class'GameplayEffect'",
      "ObjectPath": "/Script/GameplayAbilities"
    },
    "ClassFlags": "CLASS_CompiledFromBlueprint | CLASS_HasInstancedReference",
    "ClassWithin": {
      "ObjectName": "Class'Object'",
      "ObjectPath": "/Script/CoreUObject"
    },
    "ClassConfigName": "Engine",
    "bCooked": true,
    "ClassDefaultObject": {
      "ObjectName": "GE_HuskPitcherRangedCooldown_C'Default__GE_HuskPitcherRangedCooldown_C'",
      "ObjectPath": "/SaveTheWorld/Abilities/NPC/Husk/Pitcher/GE_HuskPitcherRangedCooldown.1"
    },
    "EditorTags": {
      "BlueprintType": "BPTYPE_Normal"
    }
  },
  {
    "Type": "GE_HuskPitcherRangedCooldown_C",
    "Name": "Default__GE_HuskPitcherRangedCooldown_C",
    "Flags": "RF_Public | RF_ClassDefaultObject | RF_ArchetypeObject | RF_WasLoaded | RF_LoadCompleted",
    "Class": "BlueprintGeneratedClass'/SaveTheWorld/Abilities/NPC/Husk/Pitcher/GE_HuskPitcherRangedCooldown.GE_HuskPitcherRangedCooldown_C'",
    "Properties": {
      "DurationPolicy": "EGameplayEffectDurationType::HasDuration",
      "DurationMagnitude": {
        "ScalableFloatMagnitude": {
          "Value": 0.75
        }
      },
      "InheritableOwnedTagsContainer": {
        "CombinedTags": [
          "NPC.Cooldown.Ability.Attack.Ranged"
        ],
        "Added": [
          "NPC.Cooldown.Ability.Attack.Ranged"
        ]
      },
      "GEComponents": [
        {
          "ObjectName": "TargetTagsGameplayEffectComponent'Default__GE_HuskPitcherRangedCooldown_C:TargetTagsGameplayEffectComponent_0'",
          "ObjectPath": "/SaveTheWorld/Abilities/NPC/Husk/Pitcher/GE_HuskPitcherRangedCooldown.2"
        }
      ]
    }
  },
  {
    "Type": "TargetTagsGameplayEffectComponent",
    "Name": "TargetTagsGameplayEffectComponent_0",
    "Flags": "RF_Public | RF_Transactional | RF_ArchetypeObject | RF_WasLoaded | RF_LoadCompleted",
    "Class": "UScriptClass'TargetTagsGameplayEffectComponent'",
    "Outer": {
      "ObjectName": "GE_HuskPitcherRangedCooldown_C'Default__GE_HuskPitcherRangedCooldown_C'",
      "ObjectPath": "/SaveTheWorld/Abilities/NPC/Husk/Pitcher/GE_HuskPitcherRangedCooldown.1"
    },
    "Properties": {
      "InheritableGrantedTagsContainer": {
        "CombinedTags": [
          "NPC.Cooldown.Ability.Attack.Ranged"
        ],
        "Added": [
          "NPC.Cooldown.Ability.Attack.Ranged"
        ]
      }
    }
  }
]