[
  {
    "Type": "CommonTextBlock",
    "Name": "CommonTextBlock_0",
    "Outer": "WidgetTree",
    "Class": "UScriptClass'CommonTextBlock'",
    "Flags": "RF_Transactional | RF_WasLoaded | RF_LoadCompleted",
    "Properties": {
      "Style": {
        "ObjectName": "BlueprintGeneratedClass'TextStyle-Base-ToolTip-B_C'",
        "ObjectPath": "/FortUILibrary/Styles/Typography/Foundation/TextStyle-Base-ToolTip-B.0"
      },
      "Text": {
        "Namespace": "",
        "Key": "117F965144053FA5297CD1904AA823AE",
        "SourceString": "You have XP bonuses active:",
        "LocalizedString": "You have XP bonuses active:"
      },
      "ColorAndOpacity": {
        "SpecifiedColor": {
          "R": 1.0,
          "G": 0.0,
          "B": 1.0,
          "A": 1.0,
          "Hex": "FF00FF"
        }
      },
      "Font": {
        "FontObject": null,
        "TypefaceFontName": "None"
      },
      "ShadowOffset": {
        "X": 0.0,
        "Y": 0.0
      },
      "Justification": "ETextJustify::Center",
      "AutoWrapText": true,
      "Slot": {
        "ObjectName": "VerticalBoxSlot'XpBonusToolTip_C:WidgetTree.VerticalBox_20.VerticalBoxSlot_6'",
        "ObjectPath": "/SaveTheWorld/UI/Frontend/XpBar/XpBonusToolTip.24"
      }
    }
  },
  {
    "Type": "CommonTextBlock",
    "Name": "CommonTextBlock_26",
    "Outer": "WidgetTree",
    "Class": "UScriptClass'CommonTextBlock'",
    "Flags": "RF_Transactional | RF_WasLoaded | RF_LoadCompleted",
    "Properties": {
      "Style": {
        "ObjectName": "BlueprintGeneratedClass'TextStyle-Base-ToolTip-Body_C'",
        "ObjectPath": "/FortUILibrary/Styles/Typography/Foundation/TextStyle-Base-ToolTip-Body.0"
      },
      "Text": {
        "Namespace": "",
        "Key": "8837A8164DC40A141D5C268ED306D20E",
        "SourceString": "Boosted XP",
        "LocalizedString": "Boosted XP"
      },
      "ColorAndOpacity": {
        "SpecifiedColor": {
          "R": 1.0,
          "G": 0.0,
          "B": 1.0,
          "A": 1.0,
          "Hex": "FF00FF"
        }
      },
      "Font": {
        "FontObject": null,
        "TypefaceFontName": "None"
      },
      "ShadowOffset": {
        "X": 0.0,
        "Y": 0.0
      },
      "Slot": {
        "ObjectName": "HorizontalBoxSlot'XpBonusToolTip_C:WidgetTree.HBoxBoost.HorizontalBoxSlot_27'",
        "ObjectPath": "/SaveTheWorld/UI/Frontend/XpBar/XpBonusToolTip.9"
      }
    }
  },
  {
    "Type": "CommonTextBlock",
    "Name": "CommonTextBlock_28",
    "Outer": "WidgetTree",
    "Class": "UScriptClass'CommonTextBlock'",
    "Flags": "RF_Transactional | RF_WasLoaded | RF_LoadCompleted",
    "Properties": {
      "Style": {
        "ObjectName": "BlueprintGeneratedClass'TextStyle-Base-ToolTip-Body_C'",
        "ObjectPath": "/FortUILibrary/Styles/Typography/Foundation/TextStyle-Base-ToolTip-Body.0"
      },
      "Text": {
        "Namespace": "",
        "Key": "562FBFF845DC077005A68B812488153F",
        "SourceString": "Daily Bonus XP",
        "LocalizedString": "Daily Bonus XP"
      },
      "ColorAndOpacity": {
        "SpecifiedColor": {
          "R": 1.0,
          "G": 0.0,
          "B": 1.0,
          "A": 1.0,
          "Hex": "FF00FF"
        }
      },
      "Font": {
        "FontObject": null,
        "TypefaceFontName": "None"
      },
      "ShadowOffset": {
        "X": 0.0,
        "Y": 0.0
      },
      "Slot": {
        "ObjectName": "HorizontalBoxSlot'XpBonusToolTip_C:WidgetTree.HBoxDaily.HorizontalBoxSlot_6'",
        "ObjectPath": "/SaveTheWorld/UI/Frontend/XpBar/XpBonusToolTip.11"
      }
    }
  },
  {
    "Type": "CommonTextBlock",
    "Name": "TextBoosted",
    "Outer": "WidgetTree",
    "Class": "UScriptClass'CommonTextBlock'",
    "Flags": "RF_Transactional | RF_WasLoaded | RF_LoadCompleted",
    "Properties": {
      "Style": {
        "ObjectName": "BlueprintGeneratedClass'TextStyle-Base-ToolTip-Body_C'",
        "ObjectPath": "/FortUILibrary/Styles/Typography/Foundation/TextStyle-Base-ToolTip-Body.0"
      },
      "Text": {
        "Namespace": "",
        "Key": "4201F7CD4065C4B36C4368B871C2B8C8",
        "SourceString": "Account XP will be gained at a faster rate!",
        "LocalizedString": "Account XP will be gained at a faster rate!"
      },
      "ColorAndOpacity": {
        "SpecifiedColor": {
          "R": 1.0,
          "G": 0.0,
          "B": 1.0,
          "A": 1.0,
          "Hex": "FF00FF"
        }
      },
      "Font": {
        "FontObject": null,
        "TypefaceFontName": "None"
      },
      "ShadowOffset": {
        "X": 0.0,
        "Y": 0.0
      },
      "AutoWrapText": true,
      "Slot": {
        "ObjectName": "VerticalBoxSlot'XpBonusToolTip_C:WidgetTree.VerticalBox_20.VerticalBoxSlot_4'",
        "ObjectPath": "/SaveTheWorld/UI/Frontend/XpBar/XpBonusToolTip.23"
      }
    }
  },
  {
    "Type": "Function",
    "Name": "Construct",
    "Outer": "XpBonusToolTip_C",
    "Class": "UScriptClass'Function'",
    "Flags": "RF_Public | RF_WasLoaded | RF_LoadCompleted",
    "SuperStruct": {
      "ObjectName": "Class'UserWidget:Construct'",
      "ObjectPath": "/Script/UMG"
    },
    "FunctionFlags": "FUNC_BlueprintCosmetic | FUNC_Event | FUNC_Public | FUNC_BlueprintEvent"
  },
  {
    "Type": "Function",
    "Name": "ExecuteUbergraph_XpBonusToolTip",
    "Outer": "XpBonusToolTip_C",
    "Class": "UScriptClass'Function'",
    "Flags": "RF_Public | RF_WasLoaded | RF_LoadCompleted",
    "ChildProperties": [
      {
        "Type": "IntProperty",
        "Name": "EntryPoint",
        "Flags": "RF_Public",
        "ElementSize": 4,
        "PropertyFlags": "BlueprintVisible | BlueprintReadOnly | Parm"
      },
      {
        "Type": "BoolProperty",
        "Name": "Temp_bool_Variable",
        "Flags": "RF_Public",
        "ElementSize": 1,
        "FieldSize": 1,
        "ByteOffset": 0,
        "ByteMask": 1,
        "FieldMask": 255,
        "BoolSize": 1,
        "bIsNativeBool": true
      },
      {
        "Type": "EnumProperty",
        "Name": "Temp_byte_Variable",
        "Flags": "RF_Public",
        "ElementSize": 1,
        "Enum": {
          "ObjectName": "Class'ESlateVisibility'",
          "ObjectPath": "/Script/UMG"
        },
        "UnderlyingProp": {
          "Type": "ByteProperty",
          "Name": "UnderlyingType",
          "Flags": "RF_Public",
          "ElementSize": 1,
          "Enum": null
        }
      },
      {
        "Type": "EnumProperty",
        "Name": "Temp_byte_Variable_1",
        "Flags": "RF_Public",
        "ElementSize": 1,
        "Enum": {
          "ObjectName": "Class'ESlateVisibility'",
          "ObjectPath": "/Script/UMG"
        },
        "UnderlyingProp": {
          "Type": "ByteProperty",
          "Name": "UnderlyingType",
          "Flags": "RF_Public",
          "ElementSize": 1,
          "Enum": null
        }
      },
      {
        "Type": "ObjectProperty",
        "Name": "CallFunc_GetContext_ReturnValue",
        "Flags": "RF_Public",
        "ElementSize": 8,
        "PropertyClass": {
          "ObjectName": "Class'FortMcpContext'",
          "ObjectPath": "/Script/FortniteGame"
        }
      },
      {
        "Type": "BoolProperty",
        "Name": "Temp_bool_Variable_1",
        "Flags": "RF_Public",
        "ElementSize": 1,
        "FieldSize": 1,
        "ByteOffset": 0,
        "ByteMask": 1,
        "FieldMask": 255,
        "BoolSize": 1,
        "bIsNativeBool": true
      },
      {
        "Type": "IntProperty",
        "Name": "CallFunc_GetRestXpBalance_ReturnValue",
        "Flags": "RF_Public",
        "ElementSize": 4
      },
      {
        "Type": "EnumProperty",
        "Name": "Temp_byte_Variable_2",
        "Flags": "RF_Public",
        "ElementSize": 1,
        "Enum": {
          "ObjectName": "Class'ESlateVisibility'",
          "ObjectPath": "/Script/UMG"
        },
        "UnderlyingProp": {
          "Type": "ByteProperty",
          "Name": "UnderlyingType",
          "Flags": "RF_Public",
          "ElementSize": 1,
          "Enum": null
        }
      },
      {
        "Type": "BoolProperty",
        "Name": "CallFunc_Greater_IntInt_ReturnValue",
        "Flags": "RF_Public",
        "ElementSize": 1,
        "FieldSize": 1,
        "ByteOffset": 0,
        "ByteMask": 1,
        "FieldMask": 255,
        "BoolSize": 1,
        "bIsNativeBool": true
      },
      {
        "Type": "EnumProperty",
        "Name": "Temp_byte_Variable_3",
        "Flags": "RF_Public",
        "ElementSize": 1,
        "Enum": {
          "ObjectName": "Class'ESlateVisibility'",
          "ObjectPath": "/Script/UMG"
        },
        "UnderlyingProp": {
          "Type": "ByteProperty",
          "Name": "UnderlyingType",
          "Flags": "RF_Public",
          "ElementSize": 1,
          "Enum": null
        }
      },
      {
        "Type": "EnumProperty",
        "Name": "K2Node_Select_Default",
        "Flags": "RF_Public",
        "ElementSize": 1,
        "Enum": {
          "ObjectName": "Class'ESlateVisibility'",
          "ObjectPath": "/Script/UMG"
        },
        "UnderlyingProp": {
          "Type": "ByteProperty",
          "Name": "UnderlyingType",
          "Flags": "RF_Public",
          "ElementSize": 1,
          "Enum": null
        }
      },
      {
        "Type": "ObjectProperty",
        "Name": "CallFunc_GetContext_ReturnValue_1",
        "Flags": "RF_Public",
        "ElementSize": 8,
        "PropertyClass": {
          "ObjectName": "Class'FortMcpContext'",
          "ObjectPath": "/Script/FortniteGame"
        }
      },
      {
        "Type": "IntProperty",
        "Name": "CallFunc_GetXpBoostBalance_ReturnValue",
        "Flags": "RF_Public",
        "ElementSize": 4
      },
      {
        "Type": "BoolProperty",
        "Name": "CallFunc_Greater_IntInt_ReturnValue_1",
        "Flags": "RF_Public",
        "ElementSize": 1,
        "FieldSize": 1,
        "ByteOffset": 0,
        "ByteMask": 1,
        "FieldMask": 255,
        "BoolSize": 1,
        "bIsNativeBool": true
      },
      {
        "Type": "EnumProperty",
        "Name": "K2Node_Select_Default_1",
        "Flags": "RF_Public",
        "ElementSize": 1,
        "Enum": {
          "ObjectName": "Class'ESlateVisibility'",
          "ObjectPath": "/Script/UMG"
        },
        "UnderlyingProp": {
          "Type": "ByteProperty",
          "Name": "UnderlyingType",
          "Flags": "RF_Public",
          "ElementSize": 1,
          "Enum": null
        }
      }
    ],
    "FunctionFlags": "FUNC_Final | FUNC_UbergraphFunction"
  },
  {
    "Type": "HorizontalBox",
    "Name": "HBoxBoost",
    "Outer": "WidgetTree",
    "Class": "UScriptClass'HorizontalBox'",
    "Flags": "RF_Transactional | RF_WasLoaded | RF_LoadCompleted",
    "Properties": {
      "Slots": [
        {
          "ObjectName": "HorizontalBoxSlot'XpBonusToolTip_C:WidgetTree.HBoxBoost.HorizontalBoxSlot_1'",
          "ObjectPath": "/SaveTheWorld/UI/Frontend/XpBar/XpBonusToolTip.8"
        },
        {
          "ObjectName": "HorizontalBoxSlot'XpBonusToolTip_C:WidgetTree.HBoxBoost.HorizontalBoxSlot_27'",
          "ObjectPath": "/SaveTheWorld/UI/Frontend/XpBar/XpBonusToolTip.9"
        }
      ],
      "Slot": {
        "ObjectName": "VerticalBoxSlot'XpBonusToolTip_C:WidgetTree.VerticalBox_27.VerticalBoxSlot_13'",
        "ObjectPath": "/SaveTheWorld/UI/Frontend/XpBar/XpBonusToolTip.25"
      },
      "bIsVariable": true
    }
  },
  {
    "Type": "HorizontalBox",
    "Name": "HBoxDaily",
    "Outer": "WidgetTree",
    "Class": "UScriptClass'HorizontalBox'",
    "Flags": "RF_Transactional | RF_WasLoaded | RF_LoadCompleted",
    "Properties": {
      "Slots": [
        {
          "ObjectName": "HorizontalBoxSlot'XpBonusToolTip_C:WidgetTree.HBoxDaily.HorizontalBoxSlot_5'",
          "ObjectPath": "/SaveTheWorld/UI/Frontend/XpBar/XpBonusToolTip.10"
        },
        {
          "ObjectName": "HorizontalBoxSlot'XpBonusToolTip_C:WidgetTree.HBoxDaily.HorizontalBoxSlot_6'",
          "ObjectPath": "/SaveTheWorld/UI/Frontend/XpBar/XpBonusToolTip.11"
        }
      ],
      "Slot": {
        "ObjectName": "VerticalBoxSlot'XpBonusToolTip_C:WidgetTree.VerticalBox_27.VerticalBoxSlot_14'",
        "ObjectPath": "/SaveTheWorld/UI/Frontend/XpBar/XpBonusToolTip.26"
      },
      "bIsVariable": true
    }
  },
  {
    "Type": "HorizontalBoxSlot",
    "Name": "HorizontalBoxSlot_1",
    "Outer": "HBoxBoost",
    "Class": "UScriptClass'HorizontalBoxSlot'",
    "Flags": "RF_Transactional | RF_WasLoaded | RF_LoadCompleted",
    "Properties": {
      "Padding": {
        "Left": 10.0,
        "Right": 8.0
      },
      "Parent": {
        "ObjectName": "HorizontalBox'XpBonusToolTip_C:WidgetTree.HBoxBoost'",
        "ObjectPath": "/SaveTheWorld/UI/Frontend/XpBar/XpBonusToolTip.6"
      },
      "Content": {
        "ObjectName": "Image'XpBonusToolTip_C:WidgetTree.BoostIcon'",
        "ObjectPath": "/SaveTheWorld/UI/Frontend/XpBar/XpBonusToolTip.12"
      }
    }
  },
  {
    "Type": "HorizontalBoxSlot",
    "Name": "HorizontalBoxSlot_27",
    "Outer": "HBoxBoost",
    "Class": "UScriptClass'HorizontalBoxSlot'",
    "Flags": "RF_Transactional | RF_WasLoaded | RF_LoadCompleted",
    "Properties": {
      "HorizontalAlignment": "EHorizontalAlignment::HAlign_Left",
      "VerticalAlignment": "EVerticalAlignment::VAlign_Center",
      "Parent": {
        "ObjectName": "HorizontalBox'XpBonusToolTip_C:WidgetTree.HBoxBoost'",
        "ObjectPath": "/SaveTheWorld/UI/Frontend/XpBar/XpBonusToolTip.6"
      },
      "Content": {
        "ObjectName": "CommonTextBlock'XpBonusToolTip_C:WidgetTree.CommonTextBlock_26'",
        "ObjectPath": "/SaveTheWorld/UI/Frontend/XpBar/XpBonusToolTip.1"
      }
    }
  },
  {
    "Type": "HorizontalBoxSlot",
    "Name": "HorizontalBoxSlot_5",
    "Outer": "HBoxDaily",
    "Class": "UScriptClass'HorizontalBoxSlot'",
    "Flags": "RF_Transactional | RF_WasLoaded | RF_LoadCompleted",
    "Properties": {
      "Padding": {
        "Left": 10.0,
        "Right": 8.0
      },
      "Parent": {
        "ObjectName": "HorizontalBox'XpBonusToolTip_C:WidgetTree.HBoxDaily'",
        "ObjectPath": "/SaveTheWorld/UI/Frontend/XpBar/XpBonusToolTip.7"
      },
      "Content": {
        "ObjectName": "Image'XpBonusToolTip_C:WidgetTree.Image_8'",
        "ObjectPath": "/SaveTheWorld/UI/Frontend/XpBar/XpBonusToolTip.14"
      }
    }
  },
  {
    "Type": "HorizontalBoxSlot",
    "Name": "HorizontalBoxSlot_6",
    "Outer": "HBoxDaily",
    "Class": "UScriptClass'HorizontalBoxSlot'",
    "Flags": "RF_Transactional | RF_WasLoaded | RF_LoadCompleted",
    "Properties": {
      "HorizontalAlignment": "EHorizontalAlignment::HAlign_Left",
      "VerticalAlignment": "EVerticalAlignment::VAlign_Center",
      "Parent": {
        "ObjectName": "HorizontalBox'XpBonusToolTip_C:WidgetTree.HBoxDaily'",
        "ObjectPath": "/SaveTheWorld/UI/Frontend/XpBar/XpBonusToolTip.7"
      },
      "Content": {
        "ObjectName": "CommonTextBlock'XpBonusToolTip_C:WidgetTree.CommonTextBlock_28'",
        "ObjectPath": "/SaveTheWorld/UI/Frontend/XpBar/XpBonusToolTip.2"
      }
    }
  },
  {
    "Type": "Image",
    "Name": "BoostIcon",
    "Outer": "WidgetTree",
    "Class": "UScriptClass'Image'",
    "Flags": "RF_Transactional | RF_WasLoaded | RF_LoadCompleted",
    "Properties": {
      "Brush": {
        "ResourceObject": {
          "ObjectName": "MaterialInstanceConstant'M_UI_BoostIcon_Player'",
          "ObjectPath": "/SaveTheWorld/UI/Frontend/TopBar/M_UI_BoostIcon_Player.0"
        }
      },
      "Slot": {
        "ObjectName": "HorizontalBoxSlot'XpBonusToolTip_C:WidgetTree.HBoxBoost.HorizontalBoxSlot_1'",
        "ObjectPath": "/SaveTheWorld/UI/Frontend/XpBar/XpBonusToolTip.8"
      },
      "bIsVariable": false
    }
  },
  {
    "Type": "Image",
    "Name": "Image_3",
    "Outer": "WidgetTree",
    "Class": "UScriptClass'Image'",
    "Flags": "RF_Transactional | RF_WasLoaded | RF_LoadCompleted",
    "Properties": {
      "Brush": {
        "TintColor": {
          "SpecifiedColor": {
            "R": 1.0,
            "G": 1.0,
            "B": 1.0,
            "A": 0.2,
            "Hex": "33FFFFFF"
          }
        },
        "Tiling": "ESlateBrushTileType::Horizontal",
        "ImageSize": {
          "X": 6.0,
          "Y": 2.0
        }
      },
      "Slot": {
        "ObjectName": "VerticalBoxSlot'XpBonusToolTip_C:WidgetTree.VerticalBox_0.VerticalBoxSlot_1'",
        "ObjectPath": "/SaveTheWorld/UI/Frontend/XpBar/XpBonusToolTip.20"
      },
      "bIsVariable": false
    }
  },
  {
    "Type": "Image",
    "Name": "Image_8",
    "Outer": "WidgetTree",
    "Class": "UScriptClass'Image'",
    "Flags": "RF_Transactional | RF_WasLoaded | RF_LoadCompleted",
    "Properties": {
      "Brush": {
        "ResourceObject": {
          "ObjectName": "MaterialInstanceConstant'M_UI_BoostIcon_Daily'",
          "ObjectPath": "/SaveTheWorld/UI/Frontend/TopBar/M_UI_BoostIcon_Daily.0"
        }
      },
      "Slot": {
        "ObjectName": "HorizontalBoxSlot'XpBonusToolTip_C:WidgetTree.HBoxDaily.HorizontalBoxSlot_5'",
        "ObjectPath": "/SaveTheWorld/UI/Frontend/XpBar/XpBonusToolTip.10"
      },
      "bIsVariable": false
    }
  },
  {
    "Type": "SizeBox",
    "Name": "SizeBox_0",
    "Outer": "WidgetTree",
    "Class": "UScriptClass'SizeBox'",
    "Flags": "RF_Transactional | RF_WasLoaded | RF_LoadCompleted",
    "Properties": {
      "MinDesiredWidth": 384.0,
      "MinDesiredHeight": 32.0,
      "MaxDesiredWidth": 512.0,
      "bOverride_MinDesiredWidth": true,
      "bOverride_MinDesiredHeight": true,
      "bOverride_MaxDesiredWidth": true,
      "Slots": [
        {
          "ObjectName": "SizeBoxSlot'XpBonusToolTip_C:WidgetTree.SizeBox_0.SizeBoxSlot_0'",
          "ObjectPath": "/SaveTheWorld/UI/Frontend/XpBar/XpBonusToolTip.16"
        }
      ]
    }
  },
  {
    "Type": "SizeBoxSlot",
    "Name": "SizeBoxSlot_0",
    "Outer": "SizeBox_0",
    "Class": "UScriptClass'SizeBoxSlot'",
    "Flags": "RF_Transactional | RF_WasLoaded | RF_LoadCompleted",
    "Properties": {
      "Parent": {
        "ObjectName": "SizeBox'XpBonusToolTip_C:WidgetTree.SizeBox_0'",
        "ObjectPath": "/SaveTheWorld/UI/Frontend/XpBar/XpBonusToolTip.15"
      },
      "Content": {
        "ObjectName": "VerticalBox'XpBonusToolTip_C:WidgetTree.VerticalBox_20'",
        "ObjectPath": "/SaveTheWorld/UI/Frontend/XpBar/XpBonusToolTip.18"
      }
    }
  },
  {
    "Type": "VerticalBox",
    "Name": "VerticalBox_0",
    "Outer": "WidgetTree",
    "Class": "UScriptClass'VerticalBox'",
    "Flags": "RF_Transactional | RF_WasLoaded | RF_LoadCompleted",
    "Properties": {
      "Slots": [
        {
          "ObjectName": "VerticalBoxSlot'XpBonusToolTip_C:WidgetTree.VerticalBox_0.VerticalBoxSlot_1'",
          "ObjectPath": "/SaveTheWorld/UI/Frontend/XpBar/XpBonusToolTip.20"
        }
      ],
      "Slot": {
        "ObjectName": "VerticalBoxSlot'XpBonusToolTip_C:WidgetTree.VerticalBox_20.VerticalBoxSlot_0'",
        "ObjectPath": "/SaveTheWorld/UI/Frontend/XpBar/XpBonusToolTip.21"
      }
    }
  },
  {
    "Type": "VerticalBox",
    "Name": "VerticalBox_20",
    "Outer": "WidgetTree",
    "Class": "UScriptClass'VerticalBox'",
    "Flags": "RF_Transactional | RF_WasLoaded | RF_LoadCompleted",
    "Properties": {
      "Slots": [
        {
          "ObjectName": "VerticalBoxSlot'XpBonusToolTip_C:WidgetTree.VerticalBox_20.VerticalBoxSlot_4'",
          "ObjectPath": "/SaveTheWorld/UI/Frontend/XpBar/XpBonusToolTip.23"
        },
        {
          "ObjectName": "VerticalBoxSlot'XpBonusToolTip_C:WidgetTree.VerticalBox_20.VerticalBoxSlot_6'",
          "ObjectPath": "/SaveTheWorld/UI/Frontend/XpBar/XpBonusToolTip.24"
        },
        {
          "ObjectName": "VerticalBoxSlot'XpBonusToolTip_C:WidgetTree.VerticalBox_20.VerticalBoxSlot_0'",
          "ObjectPath": "/SaveTheWorld/UI/Frontend/XpBar/XpBonusToolTip.21"
        },
        {
          "ObjectName": "VerticalBoxSlot'XpBonusToolTip_C:WidgetTree.VerticalBox_20.VerticalBoxSlot_10'",
          "ObjectPath": "/SaveTheWorld/UI/Frontend/XpBar/XpBonusToolTip.22"
        }
      ],
      "Slot": {
        "ObjectName": "SizeBoxSlot'XpBonusToolTip_C:WidgetTree.SizeBox_0.SizeBoxSlot_0'",
        "ObjectPath": "/SaveTheWorld/UI/Frontend/XpBar/XpBonusToolTip.16"
      }
    }
  },
  {
    "Type": "VerticalBox",
    "Name": "VerticalBox_27",
    "Outer": "WidgetTree",
    "Class": "UScriptClass'VerticalBox'",
    "Flags": "RF_Transactional | RF_WasLoaded | RF_LoadCompleted",
    "Properties": {
      "Slots": [
        {
          "ObjectName": "VerticalBoxSlot'XpBonusToolTip_C:WidgetTree.VerticalBox_27.VerticalBoxSlot_13'",
          "ObjectPath": "/SaveTheWorld/UI/Frontend/XpBar/XpBonusToolTip.25"
        },
        {
          "ObjectName": "VerticalBoxSlot'XpBonusToolTip_C:WidgetTree.VerticalBox_27.VerticalBoxSlot_14'",
          "ObjectPath": "/SaveTheWorld/UI/Frontend/XpBar/XpBonusToolTip.26"
        }
      ],
      "Slot": {
        "ObjectName": "VerticalBoxSlot'XpBonusToolTip_C:WidgetTree.VerticalBox_20.VerticalBoxSlot_10'",
        "ObjectPath": "/SaveTheWorld/UI/Frontend/XpBar/XpBonusToolTip.22"
      }
    }
  },
  {
    "Type": "VerticalBoxSlot",
    "Name": "VerticalBoxSlot_1",
    "Outer": "VerticalBox_0",
    "Class": "UScriptClass'VerticalBoxSlot'",
    "Flags": "RF_Transactional | RF_WasLoaded | RF_LoadCompleted",
    "Properties": {
      "Padding": {
        "Top": 4.0
      },
      "Parent": {
        "ObjectName": "VerticalBox'XpBonusToolTip_C:WidgetTree.VerticalBox_0'",
        "ObjectPath": "/SaveTheWorld/UI/Frontend/XpBar/XpBonusToolTip.17"
      },
      "Content": {
        "ObjectName": "Image'XpBonusToolTip_C:WidgetTree.Image_3'",
        "ObjectPath": "/SaveTheWorld/UI/Frontend/XpBar/XpBonusToolTip.13"
      }
    }
  },
  {
    "Type": "VerticalBoxSlot",
    "Name": "VerticalBoxSlot_0",
    "Outer": "VerticalBox_20",
    "Class": "UScriptClass'VerticalBoxSlot'",
    "Flags": "RF_Transactional | RF_WasLoaded | RF_LoadCompleted",
    "Properties": {
      "Parent": {
        "ObjectName": "VerticalBox'XpBonusToolTip_C:WidgetTree.VerticalBox_20'",
        "ObjectPath": "/SaveTheWorld/UI/Frontend/XpBar/XpBonusToolTip.18"
      },
      "Content": {
        "ObjectName": "VerticalBox'XpBonusToolTip_C:WidgetTree.VerticalBox_0'",
        "ObjectPath": "/SaveTheWorld/UI/Frontend/XpBar/XpBonusToolTip.17"
      }
    }
  },
  {
    "Type": "VerticalBoxSlot",
    "Name": "VerticalBoxSlot_10",
    "Outer": "VerticalBox_20",
    "Class": "UScriptClass'VerticalBoxSlot'",
    "Flags": "RF_Transactional | RF_WasLoaded | RF_LoadCompleted",
    "Properties": {
      "Parent": {
        "ObjectName": "VerticalBox'XpBonusToolTip_C:WidgetTree.VerticalBox_20'",
        "ObjectPath": "/SaveTheWorld/UI/Frontend/XpBar/XpBonusToolTip.18"
      },
      "Content": {
        "ObjectName": "VerticalBox'XpBonusToolTip_C:WidgetTree.VerticalBox_27'",
        "ObjectPath": "/SaveTheWorld/UI/Frontend/XpBar/XpBonusToolTip.19"
      }
    }
  },
  {
    "Type": "VerticalBoxSlot",
    "Name": "VerticalBoxSlot_4",
    "Outer": "VerticalBox_20",
    "Class": "UScriptClass'VerticalBoxSlot'",
    "Flags": "RF_Transactional | RF_WasLoaded | RF_LoadCompleted",
    "Properties": {
      "Padding": {
        "Bottom": 4.0
      },
      "Parent": {
        "ObjectName": "VerticalBox'XpBonusToolTip_C:WidgetTree.VerticalBox_20'",
        "ObjectPath": "/SaveTheWorld/UI/Frontend/XpBar/XpBonusToolTip.18"
      },
      "Content": {
        "ObjectName": "CommonTextBlock'XpBonusToolTip_C:WidgetTree.TextBoosted'",
        "ObjectPath": "/SaveTheWorld/UI/Frontend/XpBar/XpBonusToolTip.3"
      }
    }
  },
  {
    "Type": "VerticalBoxSlot",
    "Name": "VerticalBoxSlot_6",
    "Outer": "VerticalBox_20",
    "Class": "UScriptClass'VerticalBoxSlot'",
    "Flags": "RF_Transactional | RF_WasLoaded | RF_LoadCompleted",
    "Properties": {
      "HorizontalAlignment": "EHorizontalAlignment::HAlign_Left",
      "VerticalAlignment": "EVerticalAlignment::VAlign_Center",
      "Parent": {
        "ObjectName": "VerticalBox'XpBonusToolTip_C:WidgetTree.VerticalBox_20'",
        "ObjectPath": "/SaveTheWorld/UI/Frontend/XpBar/XpBonusToolTip.18"
      },
      "Content": {
        "ObjectName": "CommonTextBlock'XpBonusToolTip_C:WidgetTree.CommonTextBlock_0'",
        "ObjectPath": "/SaveTheWorld/UI/Frontend/XpBar/XpBonusToolTip.0"
      }
    }
  },
  {
    "Type": "VerticalBoxSlot",
    "Name": "VerticalBoxSlot_13",
    "Outer": "VerticalBox_27",
    "Class": "UScriptClass'VerticalBoxSlot'",
    "Flags": "RF_Transactional | RF_WasLoaded | RF_LoadCompleted",
    "Properties": {
      "Parent": {
        "ObjectName": "VerticalBox'XpBonusToolTip_C:WidgetTree.VerticalBox_27'",
        "ObjectPath": "/SaveTheWorld/UI/Frontend/XpBar/XpBonusToolTip.19"
      },
      "Content": {
        "ObjectName": "HorizontalBox'XpBonusToolTip_C:WidgetTree.HBoxBoost'",
        "ObjectPath": "/SaveTheWorld/UI/Frontend/XpBar/XpBonusToolTip.6"
      }
    }
  },
  {
    "Type": "VerticalBoxSlot",
    "Name": "VerticalBoxSlot_14",
    "Outer": "VerticalBox_27",
    "Class": "UScriptClass'VerticalBoxSlot'",
    "Flags": "RF_Transactional | RF_WasLoaded | RF_LoadCompleted",
    "Properties": {
      "Padding": {
        "Bottom": 4.0
      },
      "Parent": {
        "ObjectName": "VerticalBox'XpBonusToolTip_C:WidgetTree.VerticalBox_27'",
        "ObjectPath": "/SaveTheWorld/UI/Frontend/XpBar/XpBonusToolTip.19"
      },
      "Content": {
        "ObjectName": "HorizontalBox'XpBonusToolTip_C:WidgetTree.HBoxDaily'",
        "ObjectPath": "/SaveTheWorld/UI/Frontend/XpBar/XpBonusToolTip.7"
      }
    }
  },
  {
    "Type": "WidgetBlueprintGeneratedClass",
    "Name": "XpBonusToolTip_C",
    "Class": "UScriptClass'WidgetBlueprintGeneratedClass'",
    "Flags": "RF_Public | RF_Transactional | RF_WasLoaded | RF_LoadCompleted",
    "Properties": {
      "WidgetTree": {
        "ObjectName": "WidgetTree'XpBonusToolTip_C:WidgetTree'",
        "ObjectPath": "/SaveTheWorld/UI/Frontend/XpBar/XpBonusToolTip.28"
      },
      "UberGraphFunction": {
        "ObjectName": "Function'XpBonusToolTip_C:ExecuteUbergraph_XpBonusToolTip'",
        "ObjectPath": "/SaveTheWorld/UI/Frontend/XpBar/XpBonusToolTip.5"
      }
    },
    "SuperStruct": {
      "ObjectName": "Class'CommonUserWidget'",
      "ObjectPath": "/Script/CommonUI"
    },
    "Children": [
      {
        "ObjectName": "Function'XpBonusToolTip_C:Construct'",
        "ObjectPath": "/SaveTheWorld/UI/Frontend/XpBar/XpBonusToolTip.4"
      },
      {
        "ObjectName": "Function'XpBonusToolTip_C:ExecuteUbergraph_XpBonusToolTip'",
        "ObjectPath": "/SaveTheWorld/UI/Frontend/XpBar/XpBonusToolTip.5"
      }
    ],
    "ChildProperties": [
      {
        "Type": "StructProperty",
        "Name": "UberGraphFrame",
        "Flags": "RF_Public | RF_LoadCompleted",
        "ElementSize": 16,
        "PropertyFlags": "Transient | DuplicateTransient",
        "Struct": {
          "ObjectName": "Class'PointerToUberGraphFrame'",
          "ObjectPath": "/Script/Engine"
        }
      },
      {
        "Type": "ObjectProperty",
        "Name": "HBoxDaily",
        "Flags": "RF_Public | RF_LoadCompleted",
        "ElementSize": 8,
        "PropertyFlags": "BlueprintVisible | ExportObject | BlueprintReadOnly | DisableEditOnInstance | InstancedReference | RepSkip | PersistentInstance",
        "PropertyClass": {
          "ObjectName": "Class'HorizontalBox'",
          "ObjectPath": "/Script/UMG"
        }
      },
      {
        "Type": "ObjectProperty",
        "Name": "HBoxBoost",
        "Flags": "RF_Public | RF_LoadCompleted",
        "ElementSize": 8,
        "PropertyFlags": "BlueprintVisible | ExportObject | BlueprintReadOnly | DisableEditOnInstance | InstancedReference | RepSkip | PersistentInstance",
        "PropertyClass": {
          "ObjectName": "Class'HorizontalBox'",
          "ObjectPath": "/Script/UMG"
        }
      }
    ],
    "FuncMap": {
      "ExecuteUbergraph_XpBonusToolTip": {
        "ObjectName": "Function'XpBonusToolTip_C:ExecuteUbergraph_XpBonusToolTip'",
        "ObjectPath": "/SaveTheWorld/UI/Frontend/XpBar/XpBonusToolTip.5"
      },
      "Construct": {
        "ObjectName": "Function'XpBonusToolTip_C:Construct'",
        "ObjectPath": "/SaveTheWorld/UI/Frontend/XpBar/XpBonusToolTip.4"
      }
    },
    "ClassFlags": "CLASS_EditInlineNew | CLASS_CompiledFromBlueprint | CLASS_DefaultToInstanced | CLASS_HasInstancedReference",
    "ClassWithin": {
      "ObjectName": "Class'Object'",
      "ObjectPath": "/Script/CoreUObject"
    },
    "ClassConfigName": "Engine",
    "bCooked": true,
    "ClassDefaultObject": {
      "ObjectName": "XpBonusToolTip_C'Default__XpBonusToolTip_C'",
      "ObjectPath": "/SaveTheWorld/UI/Frontend/XpBar/XpBonusToolTip.29"
    },
    "EditorTags": {
      "BlueprintType": "BPTYPE_Normal"
    }
  },
  {
    "Type": "WidgetTree",
    "Name": "WidgetTree",
    "Outer": "XpBonusToolTip_C",
    "Class": "UScriptClass'WidgetTree'",
    "Flags": "RF_Transactional | RF_WasLoaded | RF_LoadCompleted",
    "Properties": {
      "RootWidget": {
        "ObjectName": "SizeBox'XpBonusToolTip_C:WidgetTree.SizeBox_0'",
        "ObjectPath": "/SaveTheWorld/UI/Frontend/XpBar/XpBonusToolTip.15"
      }
    }
  },
  {
    "Type": "XpBonusToolTip_C",
    "Name": "Default__XpBonusToolTip_C",
    "Class": "WidgetBlueprintGeneratedClass'/SaveTheWorld/UI/Frontend/XpBar/XpBonusToolTip.XpBonusToolTip_C'",
    "Flags": "RF_Public | RF_ClassDefaultObject | RF_ArchetypeObject | RF_WasLoaded | RF_LoadCompleted",
    "Properties": {
      "UberGraphFrame": {},
      "bHasScriptImplementedTick": false,
      "bHasScriptImplementedPaint": false
    }
  }
]