[
  {
    "Type": "AudioComponent",
    "Name": "Audio_Orb_Activation_Cue_GEN_VARIABLE",
    "Outer": "Prj_FireballProjectile_C",
    "Class": "UScriptClass'AudioComponent'",
    "Flags": "RF_Public | RF_Transactional | RF_ArchetypeObject | RF_WasLoaded | RF_LoadCompleted",
    "Properties": {
      "bAutoActivate": false
    }
  },
  {
    "Type": "AudioComponent",
    "Name": "Audio_Orb_Ambient_Loop_Cue_GEN_VARIABLE",
    "Outer": "Prj_FireballProjectile_C",
    "Class": "UScriptClass'AudioComponent'",
    "Flags": "RF_Public | RF_Transactional | RF_ArchetypeObject | RF_WasLoaded | RF_LoadCompleted",
    "Properties": {
      "bAutoActivate": false
    }
  },
  {
    "Type": "BlueprintGeneratedClass",
    "Name": "Prj_FireballProjectile_C",
    "Class": "UScriptClass'BlueprintGeneratedClass'",
    "Flags": "RF_Public | RF_Transactional | RF_WasLoaded | RF_LoadCompleted",
    "Properties": {
      "bHasCookedComponentInstancingData": true,
      "SimpleConstructionScript": {
        "ObjectName": "SimpleConstructionScript'Prj_FireballProjectile_C:SimpleConstructionScript_0'",
        "ObjectPath": "/SaveTheWorld/Items/Alteration_v2/GameplayAlterations/OnHit_SpreadFire/Prj_FireballProjectile.21"
      },
      "UberGraphFunction": {
        "ObjectName": "Function'Prj_FireballProjectile_C:ExecuteUbergraph_Prj_FireballProjectile'",
        "ObjectPath": "/SaveTheWorld/Items/Alteration_v2/GameplayAlterations/OnHit_SpreadFire/Prj_FireballProjectile.7"
      }
    },
    "SuperStruct": {
      "ObjectName": "Class'FortProjectileBase'",
      "ObjectPath": "/Script/FortniteGame"
    },
    "Children": [
      {
        "ObjectName": "Function'Prj_FireballProjectile_C:ReceiveHit'",
        "ObjectPath": "/SaveTheWorld/Items/Alteration_v2/GameplayAlterations/OnHit_SpreadFire/Prj_FireballProjectile.13"
      },
      {
        "ObjectName": "Function'Prj_FireballProjectile_C:ReceiveBeginPlay'",
        "ObjectPath": "/SaveTheWorld/Items/Alteration_v2/GameplayAlterations/OnHit_SpreadFire/Prj_FireballProjectile.12"
      },
      {
        "ObjectName": "Function'Prj_FireballProjectile_C:ReceiveActorBeginOverlap'",
        "ObjectPath": "/SaveTheWorld/Items/Alteration_v2/GameplayAlterations/OnHit_SpreadFire/Prj_FireballProjectile.11"
      },
      {
        "ObjectName": "Function'Prj_FireballProjectile_C:OnTargetDied'",
        "ObjectPath": "/SaveTheWorld/Items/Alteration_v2/GameplayAlterations/OnHit_SpreadFire/Prj_FireballProjectile.10"
      },
      {
        "ObjectName": "Function'Prj_FireballProjectile_C:OnReachedLockTargetDistanceThreshold'",
        "ObjectPath": "/SaveTheWorld/Items/Alteration_v2/GameplayAlterations/OnHit_SpreadFire/Prj_FireballProjectile.9"
      },
      {
        "ObjectName": "Function'Prj_FireballProjectile_C:HomingTargetDiedOrInvalid'",
        "ObjectPath": "/SaveTheWorld/Items/Alteration_v2/GameplayAlterations/OnHit_SpreadFire/Prj_FireballProjectile.8"
      },
      {
        "ObjectName": "Function'Prj_FireballProjectile_C:BeginMove'",
        "ObjectPath": "/SaveTheWorld/Items/Alteration_v2/GameplayAlterations/OnHit_SpreadFire/Prj_FireballProjectile.6"
      },
      {
        "ObjectName": "Function'Prj_FireballProjectile_C:ExecuteUbergraph_Prj_FireballProjectile'",
        "ObjectPath": "/SaveTheWorld/Items/Alteration_v2/GameplayAlterations/OnHit_SpreadFire/Prj_FireballProjectile.7"
      }
    ],
    "ChildProperties": [
      {
        "Type": "StructProperty",
        "Name": "UberGraphFrame",
        "Flags": "RF_Public | RF_LoadCompleted",
        "ElementSize": 16,
        "PropertyFlags": "Transient | DuplicateTransient",
        "Struct": {
          "ObjectName": "Class'PointerToUberGraphFrame'",
          "ObjectPath": "/Script/Engine"
        }
      },
      {
        "Type": "ObjectProperty",
        "Name": "Fireball",
        "Flags": "RF_Public | RF_LoadCompleted",
        "ElementSize": 8,
        "PropertyFlags": "BlueprintVisible | InstancedReference | NonTransactional",
        "PropertyClass": {
          "ObjectName": "Class'NiagaraComponent'",
          "ObjectPath": "/Script/Niagara"
        }
      },
      {
        "Type": "ObjectProperty",
        "Name": "Audio_Orb_Activation_Cue",
        "Flags": "RF_Public | RF_LoadCompleted",
        "ElementSize": 8,
        "PropertyFlags": "BlueprintVisible | InstancedReference | NonTransactional",
        "PropertyClass": {
          "ObjectName": "Class'AudioComponent'",
          "ObjectPath": "/Script/Engine"
        }
      },
      {
        "Type": "ObjectProperty",
        "Name": "Audio_Orb_Ambient_Loop_Cue",
        "Flags": "RF_Public | RF_LoadCompleted",
        "ElementSize": 8,
        "PropertyFlags": "BlueprintVisible | InstancedReference | NonTransactional",
        "PropertyClass": {
          "ObjectName": "Class'AudioComponent'",
          "ObjectPath": "/Script/Engine"
        }
      },
      {
        "Type": "StructProperty",
        "Name": "TargetLocation",
        "Flags": "RF_Public | RF_LoadCompleted",
        "ElementSize": 24,
        "PropertyFlags": "Edit | BlueprintVisible | DisableEditOnInstance",
        "Struct": {
          "ObjectName": "Class'Vector'",
          "ObjectPath": "/Script/CoreUObject"
        }
      },
      {
        "Type": "ObjectProperty",
        "Name": "HomingTarget",
        "Flags": "RF_Public | RF_LoadCompleted",
        "ElementSize": 8,
        "PropertyFlags": "Edit | BlueprintVisible | DisableEditOnTemplate | DisableEditOnInstance",
        "PropertyClass": {
          "ObjectName": "Class'Actor'",
          "ObjectPath": "/Script/Engine"
        }
      },
      {
        "Type": "StructProperty",
        "Name": "ProjectileSpeed",
        "Flags": "RF_Public | RF_LoadCompleted",
        "ElementSize": 56,
        "PropertyFlags": "Edit | BlueprintVisible | DisableEditOnInstance",
        "Struct": {
          "ObjectName": "Class'ScalableFloat'",
          "ObjectPath": "/Script/GameplayAbilities"
        }
      },
      {
        "Type": "StructProperty",
        "Name": "BackupTargetLocation",
        "Flags": "RF_Public | RF_LoadCompleted",
        "ElementSize": 24,
        "PropertyFlags": "Edit | BlueprintVisible | DisableEditOnInstance",
        "Struct": {
          "ObjectName": "Class'Vector'",
          "ObjectPath": "/Script/CoreUObject"
        }
      },
      {
        "Type": "ObjectProperty",
        "Name": "HomingTargetPawn",
        "Flags": "RF_Public | RF_LoadCompleted",
        "ElementSize": 8,
        "PropertyFlags": "Edit | BlueprintVisible | DisableEditOnTemplate | DisableEditOnInstance",
        "PropertyClass": {
          "ObjectName": "Class'FortPawn'",
          "ObjectPath": "/Script/FortniteGame"
        }
      },
      {
        "Type": "StructProperty",
        "Name": "ProjectileSpawnDelay",
        "Flags": "RF_Public | RF_LoadCompleted",
        "ElementSize": 56,
        "PropertyFlags": "Edit | BlueprintVisible | DisableEditOnInstance",
        "Struct": {
          "ObjectName": "Class'ScalableFloat'",
          "ObjectPath": "/Script/GameplayAbilities"
        }
      },
      {
        "Type": "StructProperty",
        "Name": "ProjectileHomingTurnSpeed",
        "Flags": "RF_Public | RF_LoadCompleted",
        "ElementSize": 56,
        "PropertyFlags": "Edit | BlueprintVisible | DisableEditOnInstance",
        "Struct": {
          "ObjectName": "Class'ScalableFloat'",
          "ObjectPath": "/Script/GameplayAbilities"
        }
      },
      {
        "Type": "StructProperty",
        "Name": "ProjectileDistanceThresholdToExplode",
        "Flags": "RF_Public | RF_LoadCompleted",
        "ElementSize": 56,
        "PropertyFlags": "Edit | BlueprintVisible | DisableEditOnInstance",
        "Struct": {
          "ObjectName": "Class'ScalableFloat'",
          "ObjectPath": "/Script/GameplayAbilities"
        }
      }
    ],
    "FuncMap": {
      "ExecuteUbergraph_Prj_FireballProjectile": {
        "ObjectName": "Function'Prj_FireballProjectile_C:ExecuteUbergraph_Prj_FireballProjectile'",
        "ObjectPath": "/SaveTheWorld/Items/Alteration_v2/GameplayAlterations/OnHit_SpreadFire/Prj_FireballProjectile.7"
      },
      "BeginMove": {
        "ObjectName": "Function'Prj_FireballProjectile_C:BeginMove'",
        "ObjectPath": "/SaveTheWorld/Items/Alteration_v2/GameplayAlterations/OnHit_SpreadFire/Prj_FireballProjectile.6"
      },
      "HomingTargetDiedOrInvalid": {
        "ObjectName": "Function'Prj_FireballProjectile_C:HomingTargetDiedOrInvalid'",
        "ObjectPath": "/SaveTheWorld/Items/Alteration_v2/GameplayAlterations/OnHit_SpreadFire/Prj_FireballProjectile.8"
      },
      "OnReachedLockTargetDistanceThreshold": {
        "ObjectName": "Function'Prj_FireballProjectile_C:OnReachedLockTargetDistanceThreshold'",
        "ObjectPath": "/SaveTheWorld/Items/Alteration_v2/GameplayAlterations/OnHit_SpreadFire/Prj_FireballProjectile.9"
      },
      "OnTargetDied": {
        "ObjectName": "Function'Prj_FireballProjectile_C:OnTargetDied'",
        "ObjectPath": "/SaveTheWorld/Items/Alteration_v2/GameplayAlterations/OnHit_SpreadFire/Prj_FireballProjectile.10"
      },
      "ReceiveActorBeginOverlap": {
        "ObjectName": "Function'Prj_FireballProjectile_C:ReceiveActorBeginOverlap'",
        "ObjectPath": "/SaveTheWorld/Items/Alteration_v2/GameplayAlterations/OnHit_SpreadFire/Prj_FireballProjectile.11"
      },
      "ReceiveBeginPlay": {
        "ObjectName": "Function'Prj_FireballProjectile_C:ReceiveBeginPlay'",
        "ObjectPath": "/SaveTheWorld/Items/Alteration_v2/GameplayAlterations/OnHit_SpreadFire/Prj_FireballProjectile.12"
      },
      "ReceiveHit": {
        "ObjectName": "Function'Prj_FireballProjectile_C:ReceiveHit'",
        "ObjectPath": "/SaveTheWorld/Items/Alteration_v2/GameplayAlterations/OnHit_SpreadFire/Prj_FireballProjectile.13"
      }
    },
    "ClassFlags": "CLASS_Config | CLASS_CompiledFromBlueprint | CLASS_HasInstancedReference",
    "ClassWithin": {
      "ObjectName": "Class'Object'",
      "ObjectPath": "/Script/CoreUObject"
    },
    "ClassConfigName": "Engine",
    "bCooked": true,
    "ClassDefaultObject": {
      "ObjectName": "Prj_FireballProjectile_C'Default__Prj_FireballProjectile_C'",
      "ObjectPath": "/SaveTheWorld/Items/Alteration_v2/GameplayAlterations/OnHit_SpreadFire/Prj_FireballProjectile.15"
    },
    "EditorTags": {
      "BlueprintType": "BPTYPE_Normal"
    }
  },
  {
    "Type": "FortProjectileMovementComponent",
    "Name": "ProjectileComp0",
    "Outer": "Default__Prj_FireballProjectile_C",
    "Class": "UScriptClass'FortProjectileMovementComponent'",
    "Flags": "RF_Public | RF_Transactional | RF_ArchetypeObject | RF_DefaultSubObject | RF_WasLoaded | RF_LoadCompleted",
    "Properties": {
      "AccelerationMagnitude": 1000.0,
      "bRotationFollowsVelocity": true,
      "ProjectileGravityScale": 0.0,
      "Bounciness": 0.0,
      "Friction": 1.0,
      "bAutoActivate": false
    }
  },
  {
    "Type": "FortProjectileRootComponent",
    "Name": "CollisionCapsule0",
    "Outer": "Default__Prj_FireballProjectile_C",
    "Class": "UScriptClass'FortProjectileRootComponent'",
    "Flags": "RF_Public | RF_Transactional | RF_ArchetypeObject | RF_DefaultSubObject | RF_WasLoaded | RF_LoadCompleted",
    "Properties": {
      "CapsuleHalfHeight": 20.0,
      "CapsuleRadius": 20.0,
      "bUseSystemDefaultObstacleAreaClass": false,
      "AreaClassOverride": {
        "ObjectName": "Class'FortMetaNavArea_Obstacles'",
        "ObjectPath": "/Script/FortniteAI"
      },
      "bGenerateOverlapEvents": false,
      "CanCharacterStepUpOn": "ECanBeCharacterBase::ECB_No",
      "BodyInstance": {
        "bNotifyRigidBodyCollision": true,
        "CollisionProfileName": "Custom",
        "CollisionResponses": {
          "ResponseArray": [
            {
              "Channel": "Visibility",
              "Response": "ECollisionResponse::ECR_Ignore"
            },
            {
              "Channel": "Camera",
              "Response": "ECollisionResponse::ECR_Ignore"
            },
            {
              "Channel": "PhysicsBody",
              "Response": "ECollisionResponse::ECR_Overlap"
            },
            {
              "Channel": "Vehicle",
              "Response": "ECollisionResponse::ECR_Overlap"
            },
            {
              "Channel": "FCC_Object_PawnAI",
              "Response": "ECollisionResponse::ECR_Block"
            },
            {
              "Channel": "FCC_Object_Projectile",
              "Response": "ECollisionResponse::ECR_Overlap"
            }
          ]
        }
      }
    }
  },
  {
    "Type": "FortWaterInteractionComponent",
    "Name": "WaterComponentName",
    "Outer": "Default__Prj_FireballProjectile_C",
    "Class": "UScriptClass'FortWaterInteractionComponent'",
    "Flags": "RF_Public | RF_Transactional | RF_ArchetypeObject | RF_DefaultSubObject | RF_WasLoaded | RF_LoadCompleted"
  },
  {
    "Type": "Function",
    "Name": "BeginMove",
    "Outer": "Prj_FireballProjectile_C",
    "Class": "UScriptClass'Function'",
    "Flags": "RF_Public | RF_WasLoaded | RF_LoadCompleted",
    "FunctionFlags": "FUNC_BlueprintCallable | FUNC_BlueprintEvent"
  },
  {
    "Type": "Function",
    "Name": "ExecuteUbergraph_Prj_FireballProjectile",
    "Outer": "Prj_FireballProjectile_C",
    "Class": "UScriptClass'Function'",
    "Flags": "RF_Public | RF_WasLoaded | RF_LoadCompleted",
    "ChildProperties": [
      {
        "Type": "IntProperty",
        "Name": "EntryPoint",
        "Flags": "RF_Public",
        "ElementSize": 4,
        "PropertyFlags": "BlueprintVisible | BlueprintReadOnly | Parm"
      },
      {
        "Type": "StructProperty",
        "Name": "CallFunc_K2_GetActorLocation_ReturnValue",
        "Flags": "RF_Public",
        "ElementSize": 24,
        "Struct": {
          "ObjectName": "Class'Vector'",
          "ObjectPath": "/Script/CoreUObject"
        }
      },
      {
        "Type": "ObjectProperty",
        "Name": "CallFunc_SpawnSoundAtLocation_ReturnValue",
        "Flags": "RF_Public",
        "ElementSize": 8,
        "PropertyFlags": "InstancedReference",
        "PropertyClass": {
          "ObjectName": "Class'AudioComponent'",
          "ObjectPath": "/Script/Engine"
        }
      },
      {
        "Type": "ObjectProperty",
        "Name": "K2Node_Event_MyComp",
        "Flags": "RF_Public",
        "ElementSize": 8,
        "PropertyFlags": "InstancedReference",
        "PropertyClass": {
          "ObjectName": "Class'PrimitiveComponent'",
          "ObjectPath": "/Script/Engine"
        }
      },
      {
        "Type": "ObjectProperty",
        "Name": "K2Node_Event_Other",
        "Flags": "RF_Public",
        "ElementSize": 8,
        "PropertyClass": {
          "ObjectName": "Class'Actor'",
          "ObjectPath": "/Script/Engine"
        }
      },
      {
        "Type": "ObjectProperty",
        "Name": "K2Node_Event_OtherComp",
        "Flags": "RF_Public",
        "ElementSize": 8,
        "PropertyFlags": "InstancedReference",
        "PropertyClass": {
          "ObjectName": "Class'PrimitiveComponent'",
          "ObjectPath": "/Script/Engine"
        }
      },
      {
        "Type": "BoolProperty",
        "Name": "K2Node_Event_bSelfMoved",
        "Flags": "RF_Public",
        "ElementSize": 1,
        "FieldSize": 1,
        "ByteOffset": 0,
        "ByteMask": 1,
        "FieldMask": 255,
        "BoolSize": 1,
        "bIsNativeBool": true
      },
      {
        "Type": "StructProperty",
        "Name": "K2Node_Event_HitLocation",
        "Flags": "RF_Public",
        "ElementSize": 24,
        "Struct": {
          "ObjectName": "Class'Vector'",
          "ObjectPath": "/Script/CoreUObject"
        }
      },
      {
        "Type": "StructProperty",
        "Name": "K2Node_Event_HitNormal",
        "Flags": "RF_Public",
        "ElementSize": 24,
        "Struct": {
          "ObjectName": "Class'Vector'",
          "ObjectPath": "/Script/CoreUObject"
        }
      },
      {
        "Type": "StructProperty",
        "Name": "K2Node_Event_NormalImpulse",
        "Flags": "RF_Public",
        "ElementSize": 24,
        "Struct": {
          "ObjectName": "Class'Vector'",
          "ObjectPath": "/Script/CoreUObject"
        }
      },
      {
        "Type": "StructProperty",
        "Name": "K2Node_Event_Hit",
        "Flags": "RF_Public",
        "ElementSize": 264,
        "PropertyFlags": "ConstParm | ContainsInstancedReference",
        "Struct": {
          "ObjectName": "Class'HitResult'",
          "ObjectPath": "/Script/Engine"
        }
      },
      {
        "Type": "ObjectProperty",
        "Name": "K2Node_Event_OtherActor",
        "Flags": "RF_Public",
        "ElementSize": 8,
        "PropertyClass": {
          "ObjectName": "Class'Actor'",
          "ObjectPath": "/Script/Engine"
        }
      },
      {
        "Type": "ObjectProperty",
        "Name": "K2Node_DynamicCast_AsFort_Pawn",
        "Flags": "RF_Public",
        "ElementSize": 8,
        "PropertyClass": {
          "ObjectName": "Class'FortPawn'",
          "ObjectPath": "/Script/FortniteGame"
        }
      },
      {
        "Type": "BoolProperty",
        "Name": "K2Node_DynamicCast_bSuccess",
        "Flags": "RF_Public",
        "ElementSize": 1,
        "FieldSize": 1,
        "ByteOffset": 0,
        "ByteMask": 1,
        "FieldMask": 255,
        "BoolSize": 1,
        "bIsNativeBool": true
      },
      {
        "Type": "ObjectProperty",
        "Name": "K2Node_CustomEvent_DamagedActor",
        "Flags": "RF_Public",
        "ElementSize": 8,
        "PropertyClass": {
          "ObjectName": "Class'Actor'",
          "ObjectPath": "/Script/Engine"
        }
      },
      {
        "Type": "FloatProperty",
        "Name": "K2Node_CustomEvent_Damage",
        "Flags": "RF_Public",
        "ElementSize": 4
      },
      {
        "Type": "ObjectProperty",
        "Name": "K2Node_CustomEvent_InstigatedBy",
        "Flags": "RF_Public",
        "ElementSize": 8,
        "PropertyClass": {
          "ObjectName": "Class'Controller'",
          "ObjectPath": "/Script/Engine"
        }
      },
      {
        "Type": "ObjectProperty",
        "Name": "K2Node_CustomEvent_DamageCauser",
        "Flags": "RF_Public",
        "ElementSize": 8,
        "PropertyClass": {
          "ObjectName": "Class'Actor'",
          "ObjectPath": "/Script/Engine"
        }
      },
      {
        "Type": "StructProperty",
        "Name": "K2Node_CustomEvent_HitLocation",
        "Flags": "RF_Public",
        "ElementSize": 24,
        "Struct": {
          "ObjectName": "Class'Vector'",
          "ObjectPath": "/Script/CoreUObject"
        }
      },
      {
        "Type": "ObjectProperty",
        "Name": "K2Node_CustomEvent_FHitComponent",
        "Flags": "RF_Public",
        "ElementSize": 8,
        "PropertyFlags": "InstancedReference",
        "PropertyClass": {
          "ObjectName": "Class'PrimitiveComponent'",
          "ObjectPath": "/Script/Engine"
        }
      },
      {
        "Type": "NameProperty",
        "Name": "K2Node_CustomEvent_BoneName",
        "Flags": "RF_Public",
        "ElementSize": 12
      },
      {
        "Type": "StructProperty",
        "Name": "K2Node_CustomEvent_Momentum",
        "Flags": "RF_Public",
        "ElementSize": 24,
        "Struct": {
          "ObjectName": "Class'Vector'",
          "ObjectPath": "/Script/CoreUObject"
        }
      },
      {
        "Type": "StructProperty",
        "Name": "CallFunc_K2_GetActorLocation_ReturnValue_1",
        "Flags": "RF_Public",
        "ElementSize": 24,
        "Struct": {
          "ObjectName": "Class'Vector'",
          "ObjectPath": "/Script/CoreUObject"
        }
      },
      {
        "Type": "BoolProperty",
        "Name": "CallFunc_IsValid_ReturnValue",
        "Flags": "RF_Public",
        "ElementSize": 1,
        "FieldSize": 1,
        "ByteOffset": 0,
        "ByteMask": 1,
        "FieldMask": 255,
        "BoolSize": 1,
        "bIsNativeBool": true
      },
      {
        "Type": "DelegateProperty",
        "Name": "K2Node_CreateDelegate_OutputDelegate",
        "Flags": "RF_Public",
        "ElementSize": 32,
        "SignatureFunction": {
          "ObjectName": "Class'PawnDamagedSignature__DelegateSignature'",
          "ObjectPath": "/Script/FortniteGame"
        }
      },
      {
        "Type": "BoolProperty",
        "Name": "CallFunc_IsValid_ReturnValue_1",
        "Flags": "RF_Public",
        "ElementSize": 1,
        "FieldSize": 1,
        "ByteOffset": 0,
        "ByteMask": 1,
        "FieldMask": 255,
        "BoolSize": 1,
        "bIsNativeBool": true
      },
      {
        "Type": "BoolProperty",
        "Name": "Temp_bool_B_Execution_Happened_Variable",
        "Flags": "RF_Public",
        "ElementSize": 1,
        "FieldSize": 1,
        "ByteOffset": 0,
        "ByteMask": 1,
        "FieldMask": 255,
        "BoolSize": 1,
        "bIsNativeBool": true
      },
      {
        "Type": "BoolProperty",
        "Name": "CallFunc_IsDead_ReturnValue",
        "Flags": "RF_Public",
        "ElementSize": 1,
        "FieldSize": 1,
        "ByteOffset": 0,
        "ByteMask": 1,
        "FieldMask": 255,
        "BoolSize": 1,
        "bIsNativeBool": true
      },
      {
        "Type": "BoolProperty",
        "Name": "Temp_bool_A_Execution_Happened_Variable",
        "Flags": "RF_Public",
        "ElementSize": 1,
        "FieldSize": 1,
        "ByteOffset": 0,
        "ByteMask": 1,
        "FieldMask": 255,
        "BoolSize": 1,
        "bIsNativeBool": true
      },
      {
        "Type": "BoolProperty",
        "Name": "CallFunc_Not_PreBool_ReturnValue",
        "Flags": "RF_Public",
        "ElementSize": 1,
        "FieldSize": 1,
        "ByteOffset": 0,
        "ByteMask": 1,
        "FieldMask": 255,
        "BoolSize": 1,
        "bIsNativeBool": true
      },
      {
        "Type": "BoolProperty",
        "Name": "CallFunc_BooleanAND_ReturnValue",
        "Flags": "RF_Public",
        "ElementSize": 1,
        "FieldSize": 1,
        "ByteOffset": 0,
        "ByteMask": 1,
        "FieldMask": 255,
        "BoolSize": 1,
        "bIsNativeBool": true
      },
      {
        "Type": "BoolProperty",
        "Name": "Temp_bool_IsClosed_Variable",
        "Flags": "RF_Public",
        "ElementSize": 1,
        "FieldSize": 1,
        "ByteOffset": 0,
        "ByteMask": 1,
        "FieldMask": 255,
        "BoolSize": 1,
        "bIsNativeBool": true
      },
      {
        "Type": "BoolProperty",
        "Name": "CallFunc_IsDedicatedServer_ReturnValue",
        "Flags": "RF_Public",
        "ElementSize": 1,
        "FieldSize": 1,
        "ByteOffset": 0,
        "ByteMask": 1,
        "FieldMask": 255,
        "BoolSize": 1,
        "bIsNativeBool": true
      },
      {
        "Type": "FloatProperty",
        "Name": "CallFunc_GetValueAtLevel_ReturnValue",
        "Flags": "RF_Public",
        "ElementSize": 4
      },
      {
        "Type": "BoolProperty",
        "Name": "Temp_bool_Has_Been_Initd_Variable",
        "Flags": "RF_Public",
        "ElementSize": 1,
        "FieldSize": 1,
        "ByteOffset": 0,
        "ByteMask": 1,
        "FieldMask": 255,
        "BoolSize": 1,
        "bIsNativeBool": true
      },
      {
        "Type": "FloatProperty",
        "Name": "CallFunc_GetValueAtLevel_ReturnValue_1",
        "Flags": "RF_Public",
        "ElementSize": 4
      },
      {
        "Type": "FloatProperty",
        "Name": "CallFunc_GetValueAtLevel_ReturnValue_2",
        "Flags": "RF_Public",
        "ElementSize": 4
      },
      {
        "Type": "FloatProperty",
        "Name": "CallFunc_GetValueAtLevel_ReturnValue_3",
        "Flags": "RF_Public",
        "ElementSize": 4
      },
      {
        "Type": "StructProperty",
        "Name": "K2Node_MakeStruct_ProjectileHomingData",
        "Flags": "RF_Public",
        "ElementSize": 104,
        "PropertyFlags": "ContainsInstancedReference",
        "Struct": {
          "ObjectName": "Class'ProjectileHomingData'",
          "ObjectPath": "/Script/FortniteGame"
        }
      },
      {
        "Type": "StructProperty",
        "Name": "K2Node_MakeStruct_ProjectileHomingData_1",
        "Flags": "RF_Public",
        "ElementSize": 104,
        "PropertyFlags": "ContainsInstancedReference",
        "Struct": {
          "ObjectName": "Class'ProjectileHomingData'",
          "ObjectPath": "/Script/FortniteGame"
        }
      }
    ],
    "FunctionFlags": "FUNC_Final | FUNC_UbergraphFunction | FUNC_HasDefaults"
  },
  {
    "Type": "Function",
    "Name": "HomingTargetDiedOrInvalid",
    "Outer": "Prj_FireballProjectile_C",
    "Class": "UScriptClass'Function'",
    "Flags": "RF_Public | RF_WasLoaded | RF_LoadCompleted",
    "FunctionFlags": "FUNC_BlueprintCallable | FUNC_BlueprintEvent"
  },
  {
    "Type": "Function",
    "Name": "OnReachedLockTargetDistanceThreshold",
    "Outer": "Prj_FireballProjectile_C",
    "Class": "UScriptClass'Function'",
    "Flags": "RF_Public | RF_WasLoaded | RF_LoadCompleted",
    "SuperStruct": {
      "ObjectName": "Class'FortProjectileMovementInterface:OnReachedLockTargetDistanceThreshold'",
      "ObjectPath": "/Script/FortniteGame"
    },
    "FunctionFlags": "FUNC_Event | FUNC_Public | FUNC_BlueprintEvent"
  },
  {
    "Type": "Function",
    "Name": "OnTargetDied",
    "Outer": "Prj_FireballProjectile_C",
    "Class": "UScriptClass'Function'",
    "Flags": "RF_Public | RF_WasLoaded | RF_LoadCompleted",
    "ChildProperties": [
      {
        "Type": "ObjectProperty",
        "Name": "DamagedActor",
        "Flags": "RF_Public",
        "ElementSize": 8,
        "PropertyFlags": "BlueprintVisible | BlueprintReadOnly | Parm",
        "PropertyClass": {
          "ObjectName": "Class'Actor'",
          "ObjectPath": "/Script/Engine"
        }
      },
      {
        "Type": "FloatProperty",
        "Name": "Damage",
        "Flags": "RF_Public",
        "ElementSize": 4,
        "PropertyFlags": "BlueprintVisible | BlueprintReadOnly | Parm"
      },
      {
        "Type": "ObjectProperty",
        "Name": "InstigatedBy",
        "Flags": "RF_Public",
        "ElementSize": 8,
        "PropertyFlags": "BlueprintVisible | BlueprintReadOnly | Parm",
        "PropertyClass": {
          "ObjectName": "Class'Controller'",
          "ObjectPath": "/Script/Engine"
        }
      },
      {
        "Type": "ObjectProperty",
        "Name": "DamageCauser",
        "Flags": "RF_Public",
        "ElementSize": 8,
        "PropertyFlags": "BlueprintVisible | BlueprintReadOnly | Parm",
        "PropertyClass": {
          "ObjectName": "Class'Actor'",
          "ObjectPath": "/Script/Engine"
        }
      },
      {
        "Type": "StructProperty",
        "Name": "HitLocation",
        "Flags": "RF_Public",
        "ElementSize": 24,
        "PropertyFlags": "BlueprintVisible | BlueprintReadOnly | Parm",
        "Struct": {
          "ObjectName": "Class'Vector'",
          "ObjectPath": "/Script/CoreUObject"
        }
      },
      {
        "Type": "ObjectProperty",
        "Name": "FHitComponent",
        "Flags": "RF_Public",
        "ElementSize": 8,
        "PropertyFlags": "BlueprintVisible | BlueprintReadOnly | Parm | InstancedReference",
        "PropertyClass": {
          "ObjectName": "Class'PrimitiveComponent'",
          "ObjectPath": "/Script/Engine"
        }
      },
      {
        "Type": "NameProperty",
        "Name": "BoneName",
        "Flags": "RF_Public",
        "ElementSize": 12,
        "PropertyFlags": "BlueprintVisible | BlueprintReadOnly | Parm"
      },
      {
        "Type": "StructProperty",
        "Name": "Momentum",
        "Flags": "RF_Public",
        "ElementSize": 24,
        "PropertyFlags": "BlueprintVisible | BlueprintReadOnly | Parm",
        "Struct": {
          "ObjectName": "Class'Vector'",
          "ObjectPath": "/Script/CoreUObject"
        }
      }
    ],
    "FunctionFlags": "FUNC_BlueprintCallable | FUNC_BlueprintEvent"
  },
  {
    "Type": "Function",
    "Name": "ReceiveActorBeginOverlap",
    "Outer": "Prj_FireballProjectile_C",
    "Class": "UScriptClass'Function'",
    "Flags": "RF_Public | RF_WasLoaded | RF_LoadCompleted",
    "SuperStruct": {
      "ObjectName": "Class'Actor:ReceiveActorBeginOverlap'",
      "ObjectPath": "/Script/Engine"
    },
    "ChildProperties": [
      {
        "Type": "ObjectProperty",
        "Name": "OtherActor",
        "Flags": "RF_Public",
        "ElementSize": 8,
        "PropertyFlags": "BlueprintVisible | BlueprintReadOnly | Parm",
        "PropertyClass": {
          "ObjectName": "Class'Actor'",
          "ObjectPath": "/Script/Engine"
        }
      }
    ],
    "FunctionFlags": "FUNC_Event | FUNC_Public | FUNC_BlueprintEvent"
  },
  {
    "Type": "Function",
    "Name": "ReceiveBeginPlay",
    "Outer": "Prj_FireballProjectile_C",
    "Class": "UScriptClass'Function'",
    "Flags": "RF_Public | RF_WasLoaded | RF_LoadCompleted",
    "SuperStruct": {
      "ObjectName": "Class'Actor:ReceiveBeginPlay'",
      "ObjectPath": "/Script/Engine"
    },
    "FunctionFlags": "FUNC_Event | FUNC_Protected | FUNC_BlueprintEvent"
  },
  {
    "Type": "Function",
    "Name": "ReceiveHit",
    "Outer": "Prj_FireballProjectile_C",
    "Class": "UScriptClass'Function'",
    "Flags": "RF_Public | RF_WasLoaded | RF_LoadCompleted",
    "SuperStruct": {
      "ObjectName": "Class'Actor:ReceiveHit'",
      "ObjectPath": "/Script/Engine"
    },
    "ChildProperties": [
      {
        "Type": "ObjectProperty",
        "Name": "MyComp",
        "Flags": "RF_Public",
        "ElementSize": 8,
        "PropertyFlags": "BlueprintVisible | BlueprintReadOnly | Parm | InstancedReference",
        "PropertyClass": {
          "ObjectName": "Class'PrimitiveComponent'",
          "ObjectPath": "/Script/Engine"
        }
      },
      {
        "Type": "ObjectProperty",
        "Name": "Other",
        "Flags": "RF_Public",
        "ElementSize": 8,
        "PropertyFlags": "BlueprintVisible | BlueprintReadOnly | Parm",
        "PropertyClass": {
          "ObjectName": "Class'Actor'",
          "ObjectPath": "/Script/Engine"
        }
      },
      {
        "Type": "ObjectProperty",
        "Name": "OtherComp",
        "Flags": "RF_Public",
        "ElementSize": 8,
        "PropertyFlags": "BlueprintVisible | BlueprintReadOnly | Parm | InstancedReference",
        "PropertyClass": {
          "ObjectName": "Class'PrimitiveComponent'",
          "ObjectPath": "/Script/Engine"
        }
      },
      {
        "Type": "BoolProperty",
        "Name": "bSelfMoved",
        "Flags": "RF_Public",
        "ElementSize": 1,
        "PropertyFlags": "BlueprintVisible | BlueprintReadOnly | Parm",
        "FieldSize": 1,
        "ByteOffset": 0,
        "ByteMask": 1,
        "FieldMask": 255,
        "BoolSize": 1,
        "bIsNativeBool": true
      },
      {
        "Type": "StructProperty",
        "Name": "HitLocation",
        "Flags": "RF_Public",
        "ElementSize": 24,
        "PropertyFlags": "BlueprintVisible | BlueprintReadOnly | Parm",
        "Struct": {
          "ObjectName": "Class'Vector'",
          "ObjectPath": "/Script/CoreUObject"
        }
      },
      {
        "Type": "StructProperty",
        "Name": "HitNormal",
        "Flags": "RF_Public",
        "ElementSize": 24,
        "PropertyFlags": "BlueprintVisible | BlueprintReadOnly | Parm",
        "Struct": {
          "ObjectName": "Class'Vector'",
          "ObjectPath": "/Script/CoreUObject"
        }
      },
      {
        "Type": "StructProperty",
        "Name": "NormalImpulse",
        "Flags": "RF_Public",
        "ElementSize": 24,
        "PropertyFlags": "BlueprintVisible | BlueprintReadOnly | Parm",
        "Struct": {
          "ObjectName": "Class'Vector'",
          "ObjectPath": "/Script/CoreUObject"
        }
      },
      {
        "Type": "StructProperty",
        "Name": "Hit",
        "Flags": "RF_Public",
        "ElementSize": 264,
        "PropertyFlags": "ConstParm | BlueprintVisible | BlueprintReadOnly | Parm | OutParm | ReferenceParm | ContainsInstancedReference",
        "Struct": {
          "ObjectName": "Class'HitResult'",
          "ObjectPath": "/Script/Engine"
        }
      }
    ],
    "FunctionFlags": "FUNC_Event | FUNC_Public | FUNC_HasOutParms | FUNC_BlueprintEvent"
  },
  {
    "Type": "NiagaraComponent",
    "Name": "Fireball_GEN_VARIABLE",
    "Outer": "Prj_FireballProjectile_C",
    "Class": "UScriptClass'NiagaraComponent'",
    "Flags": "RF_Public | RF_Transactional | RF_ArchetypeObject | RF_WasLoaded | RF_LoadCompleted",
    "Properties": {
      "Asset": {
        "ObjectName": "NiagaraSystem'NS_FlameBow_ExplodeProjectile'",
        "ObjectPath": "/SaveTheWorld/Items/Weapons/Ranged/Sniper/Flamebow/FX/NS_FlameBow_ExplodeProjectile.37"
      },
      "OverrideParameters": {
        "UserParameterRedirects": [
          {
            "Key": {
              "VarData": "",
              "Name": "DEBUG",
              "TypeDef": {
                "ClassStructOrEnum": {
                  "ObjectName": "Class'NiagaraBool'",
                  "ObjectPath": "/Script/Niagara"
                },
                "UnderlyingType": 2,
                "Flags": 0
              }
            },
            "Value": {
              "VarData": "",
              "Name": "User.DEBUG",
              "TypeDef": {
                "ClassStructOrEnum": {
                  "ObjectName": "Class'NiagaraBool'",
                  "ObjectPath": "/Script/Niagara"
                },
                "UnderlyingType": 2,
                "Flags": 0
              }
            }
          }
        ],
        "SortedParameterOffsets": [
          {
            "Offset": 0,
            "Name": "User.DEBUG",
            "TypeDef": {
              "ClassStructOrEnum": {
                "ObjectName": "Class'NiagaraBool'",
                "ObjectPath": "/Script/Niagara"
              },
              "UnderlyingType": 2,
              "Flags": 0
            }
          }
        ],
        "ParameterData": [
          0,
          0,
          0,
          0
        ]
      },
      "RelativeRotation": {
        "Pitch": 0.0,
        "Yaw": 180.0,
        "Roll": -0.0
      }
    }
  },
  {
    "Type": "Prj_FireballProjectile_C",
    "Name": "Default__Prj_FireballProjectile_C",
    "Class": "BlueprintGeneratedClass'/SaveTheWorld/Items/Alteration_v2/GameplayAlterations/OnHit_SpreadFire/Prj_FireballProjectile.Prj_FireballProjectile_C'",
    "Flags": "RF_Public | RF_ClassDefaultObject | RF_ArchetypeObject | RF_WasLoaded | RF_LoadCompleted",
    "Properties": {
      "UberGraphFrame": {},
      "TargetLocation": {
        "X": 0.0,
        "Y": 0.0,
        "Z": 0.0
      },
      "ProjectileSpeed": {
        "Value": 0.0,
        "Curve": {
          "CurveTable": null,
          "RowName": "Perk.Phantasm.T02.ProjectileSpeed"
        },
        "RegistryType": {
          "Name": "None"
        }
      },
      "BackupTargetLocation": {
        "X": 0.0,
        "Y": 0.0,
        "Z": 0.0
      },
      "ProjectileSpawnDelay": {
        "Value": 0.0,
        "Curve": {
          "CurveTable": null,
          "RowName": "Perk.Phantasm.T02.ProjectileSpawnDelay"
        },
        "RegistryType": {
          "Name": "None"
        }
      },
      "ProjectileHomingTurnSpeed": {
        "Value": 360.0,
        "Curve": {
          "CurveTable": null,
          "RowName": "Perk.Phantasm.T02.ProjectileHomingTurnSpeed"
        },
        "RegistryType": {
          "Name": "None"
        }
      },
      "ProjectileDistanceThresholdToExplode": {
        "Value": 16.0,
        "Curve": {
          "CurveTable": null,
          "RowName": "Perk.Phantasm.T02.ProjectileDistanceThresholdToExplode"
        },
        "RegistryType": {
          "Name": "None"
        }
      },
      "bAddOwnerVelocity": false,
      "CapsuleComponent": {
        "ObjectName": "FortProjectileRootComponent'Default__Prj_FireballProjectile_C:CollisionCapsule0'",
        "ObjectPath": "/SaveTheWorld/Items/Alteration_v2/GameplayAlterations/OnHit_SpreadFire/Prj_FireballProjectile.4"
      },
      "ProjectileMovementComponent": {
        "ObjectName": "FortProjectileMovementComponent'Default__Prj_FireballProjectile_C:ProjectileComp0'",
        "ObjectPath": "/SaveTheWorld/Items/Alteration_v2/GameplayAlterations/OnHit_SpreadFire/Prj_FireballProjectile.3"
      },
      "WaterInteractionComponent": {
        "ObjectName": "FortWaterInteractionComponent'Default__Prj_FireballProjectile_C:WaterComponentName'",
        "ObjectPath": "/SaveTheWorld/Items/Alteration_v2/GameplayAlterations/OnHit_SpreadFire/Prj_FireballProjectile.5"
      },
      "bReplicateStopSimulationLocation": true,
      "WeaponResponseType": "EFortBaseWeaponDamage::Combat",
      "EffectContainerSpecToApplyOnTouch": {
        "TargetSelection": {
          "List": [
            {
              "Shape": "EFortTargetSelectionShape::Sphere",
              "CustomShapeComponentName": "",
              "TestType": "EFortTargetSelectionTestType::Overlap",
              "PrimarySource": "EFortAbilityTargetingSource::Custom",
              "SecondarySource": "EFortAbilityTargetingSource::Max_None",
              "Range": {
                "Value": 100.0,
                "Curve": {
                  "CurveTable": null,
                  "RowName": "None"
                },
                "RegistryType": {
                  "Name": "None"
                }
              },
              "HalfExtents": {
                "X": 0.0,
                "Y": 0.0,
                "Z": 0.0
              },
              "bAlignShapeEdgeToSourceLocation": false,
              "ConeYawAngle": {
                "Value": 0.0,
                "Curve": {
                  "CurveTable": null,
                  "RowName": "None"
                },
                "RegistryType": {
                  "Name": "None"
                }
              },
              "ConePitchAngle": {
                "Value": 0.0,
                "Curve": {
                  "CurveTable": null,
                  "RowName": "None"
                },
                "RegistryType": {
                  "Name": "None"
                }
              },
              "ConeMinRadius": {
                "Value": 1.0,
                "Curve": {
                  "CurveTable": null,
                  "RowName": "None"
                },
                "RegistryType": {
                  "Name": "None"
                }
              },
              "TargetFilter": {
                "ActorTypeFilter": "EFortTargetSelectionFilter::Pawns",
                "ActorClassFilter": null,
                "bExcludeInstigator": true,
                "bUseTrapsOwningPawnAsInstigator": false,
                "bExcludeRequester": true,
                "bExcludeAllAttachedToInstigator": false,
                "bExcludeAthenaVehicleOfInstigator": false,
                "bExcludeAllAttachedToRequester": false,
                "bExcludeTargetsInEditMode": false,
                "bExcludePawnFriends": true,
                "bExcludeFriendlyAI": true,
                "bIncludeRiddenAI": false,
                "bExcludeAllAI": false,
                "bExcludePawnNeutrals": false,
                "bExcludePawnEnemies": false,
                "bExcludeNonPawnFriends": false,
                "bExcludeNonPawnEnemies": false,
                "bConsiderFriendlyFireWhenExcludingFriends": false,
                "bExcludeDBNOPawns": false,
                "bAllowDBNOOverride": false,
                "bExcludeFallingPawns": false,
                "bExcludeWaterVolumes": false,
                "bExcludeWaterBodies": true,
                "bExcludeAthenaVehicleOccupiedBySource": true,
                "bExcludeAthenaVehicleUnoccupied": false,
                "bExcludeAthenaVehicleOccupied": false,
                "bExcludePassengersInSameVehicleAsSource": false,
                "bExcludeAthenaVehicleFromObstructionChecks": false,
                "bExcludeWithoutNavigationCorridor": false,
                "bExcludeNonPlayerBuiltPieces": false,
                "bExcludePlayerBuiltPieces": false,
                "bExcludeNonBGABuildings": false,
                "bExcludeNonPhysicsSimulatedBuildingActors": false,
                "bExcludeNonBlockingHits": false,
                "bExcludeProjectiles": false,
                "bTraceComplexCollision": false,
                "bExcludeLandscape": true,
                "bExcludeLandscapeSplineActors": true,
                "bNewtonPhysicsPropsBypassAthenaFilter": false,
                "bConsiderPhysicsPawnsAsNonPlayerPawns": true,
                "bForceIncludePhysicProp": false,
                "ExclusionGameplayTags": [
                  "BGA.Propane"
                ]
              },
              "bExcludeObstructedByWorld": false,
              "ExcludeObstructedByWorldOnlyForTargetActorClasses": [],
              "bShouldAttachedActorsObstructTarget": true,
              "ObstructionExclusionGameplayTags": [],
              "bCreateHitResultWhenNoTargetsFound": false,
              "bUseProjectileRotationForDamageZones": false,
              "TargetSelectionUsage": "EFortAbilityTargetSelectionUsage::BothTargetingAndCanHit",
              "MaxTargets": 1,
              "bIncludeVehiclePassengersAsTargets": false
            }
          ]
        }
      },
      "bKillOnMaxTargetsTouched": true,
      "LifespanAfterKill": 0.0,
      "bDisableClientOverlapEvents": true,
      "CollisionComponent": {
        "ObjectName": "FortProjectileRootComponent'Default__Prj_FireballProjectile_C:CollisionCapsule0'",
        "ObjectPath": "/SaveTheWorld/Items/Alteration_v2/GameplayAlterations/OnHit_SpreadFire/Prj_FireballProjectile.4"
      },
      "bCanBeDamaged": false,
      "InitialLifeSpan": 8.0,
      "SpawnCollisionHandlingMethod": "ESpawnActorCollisionHandlingMethod::AdjustIfPossibleButAlwaysSpawn",
      "RootComponent": {
        "ObjectName": "FortProjectileRootComponent'Default__Prj_FireballProjectile_C:CollisionCapsule0'",
        "ObjectPath": "/SaveTheWorld/Items/Alteration_v2/GameplayAlterations/OnHit_SpreadFire/Prj_FireballProjectile.4"
      }
    }
  },
  {
    "Type": "SceneComponent",
    "Name": "DefaultSceneRoot_GEN_VARIABLE",
    "Outer": "Prj_FireballProjectile_C",
    "Class": "UScriptClass'SceneComponent'",
    "Flags": "RF_Public | RF_Transactional | RF_ArchetypeObject | RF_WasLoaded | RF_LoadCompleted"
  },
  {
    "Type": "SCS_Node",
    "Name": "SCS_Node_0",
    "Outer": "SimpleConstructionScript_0",
    "Class": "UScriptClass'SCS_Node'",
    "Flags": "RF_Transactional | RF_WasLoaded | RF_LoadCompleted",
    "Properties": {
      "ComponentClass": {
        "ObjectName": "Class'SceneComponent'",
        "ObjectPath": "/Script/Engine"
      },
      "ComponentTemplate": {
        "ObjectName": "SceneComponent'Prj_FireballProjectile_C:DefaultSceneRoot_GEN_VARIABLE'",
        "ObjectPath": "/SaveTheWorld/Items/Alteration_v2/GameplayAlterations/OnHit_SpreadFire/Prj_FireballProjectile.16"
      },
      "VariableGuid": "8673FBF7-460A5EF9-0856E69D-74FD04AD",
      "InternalVariableName": "DefaultSceneRoot"
    }
  },
  {
    "Type": "SCS_Node",
    "Name": "SCS_Node_1",
    "Outer": "SimpleConstructionScript_0",
    "Class": "UScriptClass'SCS_Node'",
    "Flags": "RF_Transactional | RF_WasLoaded | RF_LoadCompleted",
    "Properties": {
      "ComponentClass": {
        "ObjectName": "Class'NiagaraComponent'",
        "ObjectPath": "/Script/Niagara"
      },
      "ComponentTemplate": {
        "ObjectName": "NiagaraComponent'Prj_FireballProjectile_C:Fireball_GEN_VARIABLE'",
        "ObjectPath": "/SaveTheWorld/Items/Alteration_v2/GameplayAlterations/OnHit_SpreadFire/Prj_FireballProjectile.14"
      },
      "CookedComponentInstancingData": {
        "ChangedPropertyList": [
          {
            "PropertyName": "Asset",
            "ArrayIndex": 0,
            "PropertyScope": {
              "ObjectName": "Class'NiagaraComponent'",
              "ObjectPath": "/Script/Niagara"
            }
          },
          {
            "PropertyName": "OverrideParameters",
            "ArrayIndex": 0,
            "PropertyScope": {
              "ObjectName": "Class'NiagaraComponent'",
              "ObjectPath": "/Script/Niagara"
            }
          },
          {
            "PropertyName": "UserParameterRedirects",
            "ArrayIndex": 0,
            "PropertyScope": {
              "ObjectName": "Class'NiagaraUserRedirectionParameterStore'",
              "ObjectPath": "/Script/Niagara"
            }
          },
          {
            "PropertyName": "SortedParameterOffsets",
            "ArrayIndex": 0,
            "PropertyScope": {
              "ObjectName": "Class'NiagaraUserRedirectionParameterStore'",
              "ObjectPath": "/Script/Niagara"
            }
          },
          {
            "PropertyName": "None",
            "ArrayIndex": 0,
            "PropertyScope": {
              "ObjectName": "Class'NiagaraUserRedirectionParameterStore'",
              "ObjectPath": "/Script/Niagara"
            }
          },
          {
            "PropertyName": "ParameterData",
            "ArrayIndex": 0,
            "PropertyScope": {
              "ObjectName": "Class'NiagaraUserRedirectionParameterStore'",
              "ObjectPath": "/Script/Niagara"
            }
          },
          {
            "PropertyName": "None",
            "ArrayIndex": 0,
            "PropertyScope": {
              "ObjectName": "Class'NiagaraUserRedirectionParameterStore'",
              "ObjectPath": "/Script/Niagara"
            }
          },
          {
            "PropertyName": "RelativeRotation",
            "ArrayIndex": 0,
            "PropertyScope": {
              "ObjectName": "Class'NiagaraComponent'",
              "ObjectPath": "/Script/Niagara"
            }
          },
          {
            "PropertyName": "Yaw",
            "ArrayIndex": 0,
            "PropertyScope": {
              "ObjectName": "Class'Rotator'",
              "ObjectPath": "/Script/CoreUObject"
            }
          }
        ],
        "bHasValidCookedData": true
      },
      "ParentComponentOrVariableName": "CollisionCapsule0",
      "bIsParentComponentNative": true,
      "VariableGuid": "8A782B6B-465A7AAC-98DDDAB5-2EAA1BF4",
      "InternalVariableName": "Fireball"
    }
  },
  {
    "Type": "SCS_Node",
    "Name": "SCS_Node_4",
    "Outer": "SimpleConstructionScript_0",
    "Class": "UScriptClass'SCS_Node'",
    "Flags": "RF_Transactional | RF_WasLoaded | RF_LoadCompleted",
    "Properties": {
      "ComponentClass": {
        "ObjectName": "Class'AudioComponent'",
        "ObjectPath": "/Script/Engine"
      },
      "ComponentTemplate": {
        "ObjectName": "AudioComponent'Prj_FireballProjectile_C:Audio_Orb_Ambient_Loop_Cue_GEN_VARIABLE'",
        "ObjectPath": "/SaveTheWorld/Items/Alteration_v2/GameplayAlterations/OnHit_SpreadFire/Prj_FireballProjectile.1"
      },
      "CookedComponentInstancingData": {
        "ChangedPropertyList": [
          {
            "PropertyName": "bAutoActivate",
            "ArrayIndex": 0,
            "PropertyScope": {
              "ObjectName": "Class'AudioComponent'",
              "ObjectPath": "/Script/Engine"
            }
          }
        ],
        "bHasValidCookedData": true
      },
      "ParentComponentOrVariableName": "CollisionCapsule0",
      "bIsParentComponentNative": true,
      "VariableGuid": "44A6E25B-459B6948-977C8DA5-C753D211",
      "InternalVariableName": "Audio_Orb_Ambient_Loop_Cue"
    }
  },
  {
    "Type": "SCS_Node",
    "Name": "SCS_Node_5",
    "Outer": "SimpleConstructionScript_0",
    "Class": "UScriptClass'SCS_Node'",
    "Flags": "RF_Transactional | RF_WasLoaded | RF_LoadCompleted",
    "Properties": {
      "ComponentClass": {
        "ObjectName": "Class'AudioComponent'",
        "ObjectPath": "/Script/Engine"
      },
      "ComponentTemplate": {
        "ObjectName": "AudioComponent'Prj_FireballProjectile_C:Audio_Orb_Activation_Cue_GEN_VARIABLE'",
        "ObjectPath": "/SaveTheWorld/Items/Alteration_v2/GameplayAlterations/OnHit_SpreadFire/Prj_FireballProjectile.0"
      },
      "CookedComponentInstancingData": {
        "ChangedPropertyList": [
          {
            "PropertyName": "bAutoActivate",
            "ArrayIndex": 0,
            "PropertyScope": {
              "ObjectName": "Class'AudioComponent'",
              "ObjectPath": "/Script/Engine"
            }
          }
        ],
        "bHasValidCookedData": true
      },
      "ParentComponentOrVariableName": "CollisionCapsule0",
      "bIsParentComponentNative": true,
      "VariableGuid": "7D2A7725-434ACCAF-A5CD6EAD-3C939055",
      "InternalVariableName": "Audio_Orb_Activation_Cue"
    }
  },
  {
    "Type": "SimpleConstructionScript",
    "Name": "SimpleConstructionScript_0",
    "Outer": "Prj_FireballProjectile_C",
    "Class": "UScriptClass'SimpleConstructionScript'",
    "Flags": "RF_Transactional | RF_WasLoaded | RF_LoadCompleted",
    "Properties": {
      "RootNodes": [
        {
          "ObjectName": "SCS_Node'Prj_FireballProjectile_C:SimpleConstructionScript_0.SCS_Node_4'",
          "ObjectPath": "/SaveTheWorld/Items/Alteration_v2/GameplayAlterations/OnHit_SpreadFire/Prj_FireballProjectile.19"
        },
        {
          "ObjectName": "SCS_Node'Prj_FireballProjectile_C:SimpleConstructionScript_0.SCS_Node_5'",
          "ObjectPath": "/SaveTheWorld/Items/Alteration_v2/GameplayAlterations/OnHit_SpreadFire/Prj_FireballProjectile.20"
        },
        {
          "ObjectName": "SCS_Node'Prj_FireballProjectile_C:SimpleConstructionScript_0.SCS_Node_1'",
          "ObjectPath": "/SaveTheWorld/Items/Alteration_v2/GameplayAlterations/OnHit_SpreadFire/Prj_FireballProjectile.18"
        }
      ],
      "AllNodes": [
        {
          "ObjectName": "SCS_Node'Prj_FireballProjectile_C:SimpleConstructionScript_0.SCS_Node_4'",
          "ObjectPath": "/SaveTheWorld/Items/Alteration_v2/GameplayAlterations/OnHit_SpreadFire/Prj_FireballProjectile.19"
        },
        {
          "ObjectName": "SCS_Node'Prj_FireballProjectile_C:SimpleConstructionScript_0.SCS_Node_5'",
          "ObjectPath": "/SaveTheWorld/Items/Alteration_v2/GameplayAlterations/OnHit_SpreadFire/Prj_FireballProjectile.20"
        },
        {
          "ObjectName": "SCS_Node'Prj_FireballProjectile_C:SimpleConstructionScript_0.SCS_Node_1'",
          "ObjectPath": "/SaveTheWorld/Items/Alteration_v2/GameplayAlterations/OnHit_SpreadFire/Prj_FireballProjectile.18"
        }
      ],
      "DefaultSceneRootNode": {
        "ObjectName": "SCS_Node'Prj_FireballProjectile_C:SimpleConstructionScript_0.SCS_Node_0'",
        "ObjectPath": "/SaveTheWorld/Items/Alteration_v2/GameplayAlterations/OnHit_SpreadFire/Prj_FireballProjectile.17"
      }
    }
  }
]