[
  {
    "Type": "Material",
    "Name": "M_Spline_Helix_Energy",
    "Flags": "RF_Public | RF_Standalone | RF_Transactional | RF_WasLoaded | RF_LoadCompleted",
    "Class": "UScriptClass'Material'",
    "Properties": {
      "BlendMode": "EBlendMode::BLEND_TranslucentGreyTransmittance",
      "ShadingModel": "EMaterialShadingModel::MSM_Unlit",
      "ShadingModels": {
        "ShadingModelField": 1
      },
      "TwoSided": true,
      "bUsedWithMeshParticles": true,
      "bCanMaskedBeAssumedOpaque": true,
      "PixelDepthOffsetMode": "EPixelDepthOffsetMode::PDOM_Legacy",
      "StateId": "9C809899-ABF58324-B14A478E-8EE7AFEB",
      "ReferencedDefaultTextures": [
        {
          "ObjectName": "Texture2D'T_NoisePack_01'",
          "ObjectPath": "/Game/Global/Textures/Default/Noise/T_NoisePack_01.0"
        },
        {
          "ObjectName": "Texture2D'T_Square_Gradient_M'",
          "ObjectPath": "/Game/Effects/Fort_Effects/Textures/Masks/T_Square_Gradient_M.0"
        }
      ],
      "bIncludedInBaseGame": true
    },
    "LoadedMaterialResources": [],
    "CachedExpressionData": {
      "RuntimeEntries": {
        "ParameterInfoSet": [
          {
            "Name": "WidthBase",
            "Association": "EMaterialParameterAssociation::GlobalParameter",
            "Index": -1
          },
          {
            "Name": "WidthTop",
            "Association": "EMaterialParameterAssociation::GlobalParameter",
            "Index": -1
          },
          {
            "Name": "Desa",
            "Association": "EMaterialParameterAssociation::GlobalParameter",
            "Index": -1
          },
          {
            "Name": "UV_Distort",
            "Association": "EMaterialParameterAssociation::GlobalParameter",
            "Index": -1
          },
          {
            "Name": "FX Emissive EyeAdaptation Alpha",
            "Association": "EMaterialParameterAssociation::GlobalParameter",
            "Index": -1
          },
          {
            "Name": "FX Emissive EyeAdaptation Prescale",
            "Association": "EMaterialParameterAssociation::GlobalParameter",
            "Index": -1
          }
        ]
      },
      "RuntimeEntries[1]": {
        "ParameterInfoSet": [
          {
            "Name": "TileBaseTexture",
            "Association": "EMaterialParameterAssociation::GlobalParameter",
            "Index": -1
          },
          {
            "Name": "TileMaskTexture",
            "Association": "EMaterialParameterAssociation::GlobalParameter",
            "Index": -1
          }
        ]
      },
      "RuntimeEntries[2]": {
        "ParameterInfoSet": []
      },
      "RuntimeEntries[3]": {
        "ParameterInfoSet": [
          {
            "Name": "DistortNoise",
            "Association": "EMaterialParameterAssociation::GlobalParameter",
            "Index": -1
          },
          {
            "Name": "BasicNoise",
            "Association": "EMaterialParameterAssociation::GlobalParameter",
            "Index": -1
          },
          {
            "Name": "Mask",
            "Association": "EMaterialParameterAssociation::GlobalParameter",
            "Index": -1
          }
        ]
      },
      "RuntimeEntries[4]": {
        "ParameterInfoSet": []
      },
      "RuntimeEntries[5]": {
        "ParameterInfoSet": []
      },
      "RuntimeEntries[6]": {
        "ParameterInfoSet": []
      },
      "RuntimeEntries[7]": {
        "ParameterInfoSet": []
      },
      "RuntimeEntries[8]": {
        "ParameterInfoSet": [
          {
            "Name": "FX Emissive EyeAdaptation",
            "Association": "EMaterialParameterAssociation::GlobalParameter",
            "Index": -1
          }
        ]
      },
      "RuntimeEntries[9]": {
        "ParameterInfoSet": []
      },
      "ScalarPrimitiveDataIndexValues": [
        -1,
        -1,
        -1,
        -1,
        -1,
        -1
      ],
      "VectorPrimitiveDataIndexValues": [
        -1,
        -1
      ],
      "ScalarValues": [
        10.0,
        10.0,
        0.82,
        10.0,
        1.0,
        1.68
      ],
      "StaticSwitchValues": [
        true
      ],
      "DynamicSwitchValues": [
        false
      ],
      "VectorValues": [
        {
          "R": 1.0,
          "G": 1.0,
          "B": 0.0,
          "A": 0.0,
          "Hex": "FFFF00"
        },
        {
          "R": 1.0,
          "G": 0.6,
          "B": 0.0,
          "A": 0.0,
          "Hex": "FFCC00"
        }
      ],
      "DoubleVectorValues": [],
      "TextureValues": [
        {
          "AssetPathName": "/Game/Global/Textures/Default/Noise/T_NoisePack_01.T_NoisePack_01",
          "SubPathString": ""
        },
        {
          "AssetPathName": "/Game/Global/Textures/Default/Noise/T_NoisePack_01.T_NoisePack_01",
          "SubPathString": ""
        },
        {
          "AssetPathName": "/Game/Effects/Fort_Effects/Textures/Masks/T_Square_Gradient_M.T_Square_Gradient_M",
          "SubPathString": ""
        }
      ],
      "TextureCollectionValues": [],
      "ParameterCollectionValues": [],
      "FontValues": [],
      "FontPageValues": [],
      "RuntimeVirtualTextureValues": [],
      "SparseVolumeTextureValues": [],
      "ReferencedTextureCollections": [],
      "ReferencedExternalCodeExpressionClasses": [
        {
          "ObjectName": "Class'MaterialExpressionParticleColor'",
          "ObjectPath": "/Script/Engine"
        },
        {
          "ObjectName": "Class'MaterialExpressionEyeAdaptationInverse'",
          "ObjectPath": "/Script/Engine"
        },
        {
          "ObjectName": "Class'MaterialExpressionEyeAdaptation'",
          "ObjectPath": "/Script/Engine"
        }
      ],
      "FunctionInfos": [
        {
          "StateId": "972EFAAA-4C1C2B16-4BC287A2-B11C51DA",
          "Function": {
            "ObjectName": "MaterialFunction'SafeNormalize'",
            "ObjectPath": "/Engine/Functions/Engine_MaterialFunctions02/SafeNormalize.0"
          }
        },
        {
          "StateId": "972EFAAA-4C1C2B16-4BC287A2-B11C51DA",
          "Function": {
            "ObjectName": "MaterialFunction'SafeNormalize'",
            "ObjectPath": "/Engine/Functions/Engine_MaterialFunctions02/SafeNormalize.0"
          }
        },
        {
          "StateId": "B404464D-42313D79-E67091AA-AD61BE51",
          "Function": {
            "ObjectName": "MaterialFunction'CreateThirdOrthogonalVector'",
            "ObjectPath": "/Engine/Functions/Engine_MaterialFunctions02/Math/CreateThirdOrthogonalVector.0"
          }
        },
        {
          "StateId": "2D5E7622-46ABF521-9F13C0AE-BCAA7138",
          "Function": {
            "ObjectName": "MaterialFunction'BreakOutFloat3Components'",
            "ObjectPath": "/Engine/Functions/Engine_MaterialFunctions02/Utility/BreakOutFloat3Components.0"
          }
        },
        {
          "StateId": "C330DE33-4A86FAB2-7255B1AC-3A6AC1B4",
          "Function": {
            "ObjectName": "MaterialFunction'Transform3x3Matrix'",
            "ObjectPath": "/Engine/Functions/Engine_MaterialFunctions02/Math/Transform3x3Matrix.0"
          }
        },
        {
          "StateId": "2C0AFCEF-4B67951F-85943A89-8827DBDF",
          "Function": {
            "ObjectName": "MaterialFunction'TangentBasis'",
            "ObjectPath": "/Engine/Functions/Engine_MaterialFunctions02/TangentBasis.0"
          }
        },
        {
          "StateId": "9AC177A3-46FF47FE-A90188B4-A4EB7FA6",
          "Function": {
            "ObjectName": "MaterialFunction'BlendAngleCorrectedNormals'",
            "ObjectPath": "/Engine/Functions/Engine_MaterialFunctions02/Utility/BlendAngleCorrectedNormals.0"
          }
        },
        {
          "StateId": "6BB97146-49B75878-03A98399-9B3C01AF",
          "Function": {
            "ObjectName": "MaterialFunction'VectorLength'",
            "ObjectPath": "/Engine/Functions/Engine_MaterialFunctions02/Utility/VectorLength.0"
          }
        },
        {
          "StateId": "6BB97146-49B75878-03A98399-9B3C01AF",
          "Function": {
            "ObjectName": "MaterialFunction'VectorLength'",
            "ObjectPath": "/Engine/Functions/Engine_MaterialFunctions02/Utility/VectorLength.0"
          }
        },
        {
          "StateId": "2D5E7622-46ABF521-9F13C0AE-BCAA7138",
          "Function": {
            "ObjectName": "MaterialFunction'BreakOutFloat3Components'",
            "ObjectPath": "/Engine/Functions/Engine_MaterialFunctions02/Utility/BreakOutFloat3Components.0"
          }
        },
        {
          "StateId": "C330DE33-4A86FAB2-7255B1AC-3A6AC1B4",
          "Function": {
            "ObjectName": "MaterialFunction'Transform3x3Matrix'",
            "ObjectPath": "/Engine/Functions/Engine_MaterialFunctions02/Math/Transform3x3Matrix.0"
          }
        },
        {
          "StateId": "972EFAAA-4C1C2B16-4BC287A2-B11C51DA",
          "Function": {
            "ObjectName": "MaterialFunction'SafeNormalize'",
            "ObjectPath": "/Engine/Functions/Engine_MaterialFunctions02/SafeNormalize.0"
          }
        },
        {
          "StateId": "972EFAAA-4C1C2B16-4BC287A2-B11C51DA",
          "Function": {
            "ObjectName": "MaterialFunction'SafeNormalize'",
            "ObjectPath": "/Engine/Functions/Engine_MaterialFunctions02/SafeNormalize.0"
          }
        },
        {
          "StateId": "B404464D-42313D79-E67091AA-AD61BE51",
          "Function": {
            "ObjectName": "MaterialFunction'CreateThirdOrthogonalVector'",
            "ObjectPath": "/Engine/Functions/Engine_MaterialFunctions02/Math/CreateThirdOrthogonalVector.0"
          }
        },
        {
          "StateId": "949B5345-47E4ADAB-4A089BB4-15A81F3F",
          "Function": {
            "ObjectName": "MaterialFunction'SplineThicken'",
            "ObjectPath": "/Engine/Functions/Engine_MaterialFunctions01/WorldPositionOffset/SplineThicken.0"
          }
        },
        {
          "StateId": "22DADBDB-40F87C73-5DFD43AD-510A7E06",
          "Function": {
            "ObjectName": "MaterialFunction'BreakOutFloat2Components'",
            "ObjectPath": "/Engine/Functions/Engine_MaterialFunctions02/Utility/BreakOutFloat2Components.0"
          }
        },
        {
          "StateId": "22C43E64-4A177A4B-5B5524B9-198443D0",
          "Function": {
            "ObjectName": "MaterialFunction'MF_FX_EmissiveAdjustments'",
            "ObjectPath": "/Game/Effects/Niagara/MasterMaterials/Functions/MF_FX_EmissiveAdjustments.0"
          }
        }
      ],
      "FunctionInfosStateCRC": 2770955780,
      "ParameterCollectionInfos": [],
      "GrassTypes": [],
      "MaterialCacheTags": [],
      "MaterialLayers": {
        "Layers": [],
        "Blends": []
      },
      "DynamicParameterNames": [
        "Random",
        "PanCurve",
        "Vtile",
        "PanSpeed"
      ],
      "QualityLevelsUsed": [
        false,
        false,
        false,
        false
      ],
      "MaterialCacheUVCoordinatesUsedMask": 0,
      "bHasMaterialLayers": false,
      "bHasRuntimeVirtualTextureOutput": false,
      "bHasFirstPersonOutput": false,
      "bUsesTemporalResponsiveness": false,
      "bUsesMotionVectorWorldOffset": false,
      "bSamplesMaterialCache": false,
      "bHasMaterialCacheOutput": false,
      "bMaterialCacheHasNonUVDerivedExpression": false,
      "bHasSceneColor": false,
      "bHasPerInstanceCustomData": false,
      "bHasPerInstanceRandom": false,
      "bHasVertexInterpolator": false,
      "bHasCustomizedUVs": false,
      "bHasMeshPaintTexture": false,
      "bHasWorldPosition": true,
      "PropertyConnectedMask": 4099
    },
    "ReferencedTextures": [
      {
        "ObjectName": "Texture2D'T_Square_Gradient_M'",
        "ObjectPath": "/Game/Effects/Fort_Effects/Textures/Masks/T_Square_Gradient_M.0"
      },
      {
        "ObjectName": "Texture2D'T_NoisePack_01'",
        "ObjectPath": "/Game/Global/Textures/Default/Noise/T_NoisePack_01.0"
      }
    ]
  }
]