[
  {
    "Type": "Texture2D",
    "Name": "Rating-Icon_48",
    "Flags": "RF_Public | RF_Standalone | RF_WasLoaded | RF_LoadCompleted",
    "Class": "UScriptClass'Texture2D'",
    "Properties": {
      "AddressX": "TextureAddress::TA_Clamp",
      "AddressY": "TextureAddress::TA_Clamp",
      "ImportedSize": {
        "X": 48,
        "Y": 26
      },
      "LightingGuid": "8B18CDFC-4E59CF2A-23E1A694-B0AB9C13",
      "CompressionSettings": "TextureCompressionSettings::TC_EditorIcon",
      "LODGroup": "TextureGroup::TEXTUREGROUP_UI",
      "NeverStream": true
    },
    "SizeX": 48,
    "SizeY": 26,
    "PackedData": 1,
    "PixelFormat": "PF_B8G8R8A8",
    "FirstMipToSerialize": 0,
    "Mips": [
      {
        "BulkData": {
          "BulkDataFlags": "BULKDATA_SingleUse | BULKDATA_ForceInlinePayload",
          "ElementCount": 4992,
          "SizeOnDisk": 4992,
          "OffsetInFile": "0x7D"
        },
        "SizeX": 48,
        "SizeY": 26,
        "SizeZ": 1
      }
    ]
  }
]