{
  "id": "ManagerInventor_SR_square_T01",
  "name": "Alfred \"Square\" Winestein",
  "description": "Alfred is all about relativity and fitting things in squares. Alfred is a lead survivor that provides increased power in The Think Tank squad.",
  "rarity": "Mythic",
  "gender": "Male",
  "isManager": true,
  "personality": "IsPragmatic",
  "squadRole": "IsInventor",
  "tier": "I",
  "rating": {
    "table": "CurveTable'SurvivorItemRating'",
    "row": "Manager_SR_T01"
  },
  "icon": "/Game/UI/Foundation/Textures/Icons/Workers/Generic/GenericWorker.png",
  "minLevel": 1,
  "maxLevel": 10,
  "traits": [
    "Item.Trait.InventorySizeLimited"
  ],
  "matchingBonus": 8,
  "mismatchPenalty": -2
}