[
  {
    "Type": "SoundWave",
    "Name": "Bow_Flame_Passby_Close_06",
    "Class": "UScriptClass'SoundWave'",
    "Flags": "RF_Public | RF_Standalone | RF_Transactional | RF_WasLoaded | RF_LoadCompleted",
    "Properties": {
      "CompressionQuality": 60,
      "NumChannels": 1,
      "SampleRate": 48000,
      "Duration": 1.9069166,
      "TotalSamples": 91532.0
    },
    "PlatformCuePoints": [],
    "CompressedFormatData": null,
    "RawData": null,
    "CompressedDataGuid": "24C92C91-4C539758-60D233BA-9B415F7A",
    "RunningPlatformData": {
      "NumChunks": 2,
      "AudioFormat": "RADA",
      "Chunks": [
        {
          "DataSize": 168,
          "AudioDataSize": 168,
          "SeekOffsetInAudioFrames": 0,
          "BulkData": {
            "BulkDataFlags": "BULKDATA_ForceInlinePayload",
            "ElementCount": 168,
            "SizeOnDisk": 168,
            "OffsetInFile": "0x4C"
          }
        },
        {
          "DataSize": 11509,
          "AudioDataSize": 11509,
          "SeekOffsetInAudioFrames": 0,
          "BulkData": {
            "BulkDataFlags": "BULKDATA_PayloadAtEndOfFile | BULKDATA_PayloadInSeperateFile | BULKDATA_Force_NOT_InlinePayload | BULKDATA_NoOffsetFixUp",
            "ElementCount": 11509,
            "SizeOnDisk": 11509,
            "OffsetInFile": "0x0"
          }
        }
      ]
    }
  }
]