{
  "id": "HID_Commando_017_F_V1_VR",
  "class": "Commando",
  "attributeCategory": "Soldier",
  "attributeSubCategory": "Soldier_Health_VR_T1",
  "name": "First Shot Rio",
  "description": "\"But, I only need one!\" - Rio",
  "shortDescription": "Hero",
  "rarity": "Epic",
  "icon": "/BRCosmetics/UI/Foundation/Textures/Icons/Heroes/Soldier/Portrait/T-Soldier-HID-Commando-017-F-V1-VR-T02.png",
  "largeIcon": "/BRCosmetics/UI/Foundation/Textures/Icons/Heroes/Soldier/Portrait/T-Soldier-HID-Commando-017-F-V1-VR-T02-L.png",
  "itemTags": [
    "Homebase.Class.IsCommando.OneShot",
    "SpecialEvent.2018.RoadTrip.Heroes.Commando.Female"
  ],
  "tags": [
    "Homebase.Class.IsCommando.OneShot",
    "SpecialEvent.2018.RoadTrip.Heroes.Commando.Female"
  ],
  "traits": [
    "Item.Trait.InventorySizeLimited"
  ],
  "tiers": [
    {
      "tier": "I",
      "minLevel": 1,
      "maxLevel": 10,
      "rating": "Default_VR_T01",
      "evolveCost": [
        {
          "item": "peoplexp",
          "quantity": 2000,
          "name": "People XP",
          "icon": "/Game/UI/Foundation/Textures/Icons/Items/T-CrewXP.png",
          "rarity": "Common"
        },
        {
          "item": "reagent_c_t01",
          "quantity": 15,
          "name": "Pure Drop of Rain",
          "icon": "/SaveTheWorld/UI/Foundation/Textures/Icons/Items/T-Items-Reagent-C-T01.png",
          "rarity": "Epic"
        },
        {
          "item": "reagent_people",
          "quantity": 50,
          "name": "Training Manual",
          "icon": "/SaveTheWorld/UI/Foundation/Textures/Icons/Items/T-Items-Reagent-People.png",
          "rarity": "Common"
        }
      ]
    },
    {
      "tier": "II",
      "minLevel": 10,
      "maxLevel": 20,
      "rating": "Default_VR_T02",
      "evolveCost": [
        {
          "item": "peoplexp",
          "quantity": 5000,
          "name": "People XP",
          "icon": "/Game/UI/Foundation/Textures/Icons/Items/T-CrewXP.png",
          "rarity": "Common"
        },
        {
          "item": "reagent_c_t01",
          "quantity": 30,
          "name": "Pure Drop of Rain",
          "icon": "/SaveTheWorld/UI/Foundation/Textures/Icons/Items/T-Items-Reagent-C-T01.png",
          "rarity": "Epic"
        },
        {
          "item": "reagent_people",
          "quantity": 125,
          "name": "Training Manual",
          "icon": "/SaveTheWorld/UI/Foundation/Textures/Icons/Items/T-Items-Reagent-People.png",
          "rarity": "Common"
        },
        {
          "item": "reagent_c_t02",
          "quantity": 9,
          "name": "Lightning in a Bottle",
          "icon": "/SaveTheWorld/UI/Foundation/Textures/Icons/Items/T-Items-Reagent-C-T02.png",
          "rarity": "Epic"
        }
      ]
    },
    {
      "tier": "III",
      "minLevel": 20,
      "maxLevel": 30,
      "rating": "Default_VR_T03",
      "evolveCost": [
        {
          "item": "peoplexp",
          "quantity": 8000,
          "name": "People XP",
          "icon": "/Game/UI/Foundation/Textures/Icons/Items/T-CrewXP.png",
          "rarity": "Common"
        },
        {
          "item": "reagent_c_t01",
          "quantity": 45,
          "name": "Pure Drop of Rain",
          "icon": "/SaveTheWorld/UI/Foundation/Textures/Icons/Items/T-Items-Reagent-C-T01.png",
          "rarity": "Epic"
        },
        {
          "item": "reagent_people",
          "quantity": 225,
          "name": "Training Manual",
          "icon": "/SaveTheWorld/UI/Foundation/Textures/Icons/Items/T-Items-Reagent-People.png",
          "rarity": "Common"
        },
        {
          "item": "reagent_c_t02",
          "quantity": 18,
          "name": "Lightning in a Bottle",
          "icon": "/SaveTheWorld/UI/Foundation/Textures/Icons/Items/T-Items-Reagent-C-T02.png",
          "rarity": "Epic"
        },
        {
          "item": "reagent_c_t03",
          "quantity": 9,
          "name": "Eye of the Storm",
          "icon": "/SaveTheWorld/UI/Foundation/Textures/Icons/Items/T-Items-Reagent-C-T03.png",
          "rarity": "Epic"
        }
      ]
    },
    {
      "tier": "IV",
      "minLevel": 30,
      "maxLevel": 40,
      "rating": "Default_VR_T04",
      "evolveCost": [
        {
          "item": "peoplexp",
          "quantity": 11000,
          "name": "People XP",
          "icon": "/Game/UI/Foundation/Textures/Icons/Items/T-CrewXP.png",
          "rarity": "Common"
        },
        {
          "item": "reagent_c_t01",
          "quantity": 60,
          "name": "Pure Drop of Rain",
          "icon": "/SaveTheWorld/UI/Foundation/Textures/Icons/Items/T-Items-Reagent-C-T01.png",
          "rarity": "Epic"
        },
        {
          "item": "reagent_people",
          "quantity": 300,
          "name": "Training Manual",
          "icon": "/SaveTheWorld/UI/Foundation/Textures/Icons/Items/T-Items-Reagent-People.png",
          "rarity": "Common"
        },
        {
          "item": "reagent_c_t02",
          "quantity": 27,
          "name": "Lightning in a Bottle",
          "icon": "/SaveTheWorld/UI/Foundation/Textures/Icons/Items/T-Items-Reagent-C-T02.png",
          "rarity": "Epic"
        },
        {
          "item": "reagent_c_t03",
          "quantity": 18,
          "name": "Eye of the Storm",
          "icon": "/SaveTheWorld/UI/Foundation/Textures/Icons/Items/T-Items-Reagent-C-T03.png",
          "rarity": "Epic"
        },
        {
          "item": "reagent_c_t04",
          "quantity": 9,
          "name": "Storm Shard",
          "icon": "/SaveTheWorld/UI/Foundation/Textures/Icons/Items/T-Items-Reagent-C-T04.png",
          "rarity": "Epic"
        }
      ]
    },
    {
      "tier": "V",
      "minLevel": 40,
      "maxLevel": 60,
      "rating": "Default_VR_T05",
      "evolveCost": []
    }
  ],
  "perks": {
    "heroPerk": {
      "id": "Kit_Perk_H_FirstAssault_T01",
      "name": "First Assault",
      "icon": "/SaveTheWorld/UI/Foundation/Textures/Icons/Heroes/Soldier/Perks/Icon-Soldier-FirstAssault-128.png",
      "tooltipId": "TT_Perk_H_FirstAssault_T01",
      "description": "After reloading or overheating <WeaponClass>Assault</> weapons or <WeaponClass>SMGs</>, the next <Number>2 shots</> have <Number>100%</> <ModifiedAttribute>Critical Chance</>."
    },
    "commanderPerk": {
      "id": "Kit_Perk_H_FirstAssault_T02",
      "name": "First Assault +",
      "icon": "/SaveTheWorld/UI/Foundation/Textures/Icons/Heroes/Soldier/Perks/Icon-Soldier-FirstAssault-128.png",
      "tooltipId": "TT_Perk_H_FirstAssault_T02",
      "description": "After reloading or overheating <WeaponClass>Assault</> weapons or <WeaponClass>SMGs</>, the next <Number>6 shots</> have <Number>100%</> <ModifiedAttribute>Critical Chance</>."
    },
    "abilities": [
      {
        "id": "Kit_Commando_WarCry",
        "name": "War Cry",
        "icon": "/SaveTheWorld/UI/Foundation/Textures/Icons/Heroes/Soldier/Abilities/Icon-Soldier-WarCry-128.png",
        "tooltipId": "TT_Commando_WarCry",
        "description": "Shout an inspiring War Cry, granting nearby allies +1.45 weapon damage, +130 fire rate, and +120 melee attack speed for 12 seconds.",
        "minRarity": "Uncommon"
      },
      {
        "id": "Kit_Commando_FragGrenade",
        "name": "Frag Grenade",
        "icon": "/BRCosmetics/UI/Foundation/Textures/Icons/Heroes/Soldier/Abilities/Icon-Soldier-Grenade-128.png",
        "tooltipId": "TT_Commando_FragGrenade",
        "description": "Throw a grenade which deals [Damage.Value] energy damage in a [Radius] radius.",
        "minRarity": "Uncommon"
      },
      {
        "id": "Kit_Commando_Shockwave",
        "name": "Shockwave",
        "icon": "/SaveTheWorld/UI/Foundation/Textures/Icons/Heroes/Soldier/Abilities/Icon-Soldier-Shockwave-128.png",
        "tooltipId": "TT_Commando_Shockwave",
        "description": "Slam a grenade into the ground, knocking back and dealing [Damage.Value] energy damage to nearby enemies.",
        "minRarity": "Uncommon"
      }
    ]
  },
  "recruitment": {
    "slotId": "HID.Commando.017.F.V1.VR.T01",
    "sourceId": "wildwest_cardpack",
    "sourceText": "Found inside Wild West X-Ray Llamas in the Llama Shop.",
    "isRecruitable": true,
    "recipe": "Creation.CollectionBook.Hero.VR"
  },
  "recruitmentCost": {
    "type": "Voucher",
    "amount": 1
  }
}